[{"itemID":"2379231","itemInfo":"Intel Core i3-3220 3.3Ghz Socket 1155 procesor","itemPrice":3680,"itemStartPrice":3680,"percentChange":0,"priceChange":0,"timeAdded":1598968803733,"timeUpdated":1598968803733,"timeLastSeen":1600092003147,"dateAdded":"01-09-2020","dateUpdated":"01-09-2020","itemLink":"https://www.nabava.net/procesori/intel-core-i3-3220-33ghz-socket-1155-procesor-cijena-2379231"},{"itemID":"6728571","itemInfo":"Intel Core i7-5930K 3.5Ghz Socket 2011 procesor","itemPrice":2075,"itemStartPrice":2922,"percentChange":-29,"priceChange":-847,"timeAdded":1596031203407,"timeUpdated":1599832803853,"timeLastSeen":1600092003147,"dateAdded":"29-07-2020","dateUpdated":"14-09-2020","itemLink":"https://www.nabava.net/procesori/intel-core-i7-5930k-35ghz-socket-2011-procesor-cijena-6728571"},{"itemID":"6728581","itemInfo":"Intel Core i7-5820K 3.3Ghz Socket 2011 procesor","itemPrice":2011,"itemStartPrice":2004,"percentChange":1,"priceChange":7,"timeAdded":1599228003934,"timeUpdated":1599228003934,"timeLastSeen":1600092003147,"dateAdded":"04-09-2020","dateUpdated":"14-09-2020","itemLink":"https://www.nabava.net/procesori/intel-core-i7-5820k-33ghz-socket-2011-procesor-cijena-6728581"},{"itemID":"15647811","itemInfo":"Intel Core i5-6600K 3.5Ghz Socket 1151 procesor","itemPrice":1650,"itemStartPrice":1730,"percentChange":-5,"priceChange":-80,"timeAdded":1599141603573,"timeUpdated":1599141603573,"timeLastSeen":1600092003147,"dateAdded":"03-09-2020","dateUpdated":"08-09-2020","itemLink":"https://www.nabava.net/procesori/intel-core-i5-6600k-35ghz-socket-1151-procesor-cijena-15647811"},{"itemID":"16790531","itemInfo":"Intel Core i5-6600 3.3Ghz Socket 1151 procesor","itemPrice":2012,"itemStartPrice":2012,"percentChange":0,"priceChange":0,"timeAdded":1599487203813,"timeUpdated":1599487203813,"timeLastSeen":1600092003147,"dateAdded":"07-09-2020","dateUpdated":"07-09-2020","itemLink":"https://www.nabava.net/procesori/intel-core-i5-6600-33ghz-socket-1151-procesor-cijena-16790531"},{"itemID":"16855111","itemInfo":"Intel Core i7-6700 3.4Ghz Socket 1151 procesor","itemPrice":24060,"itemStartPrice":11220,"percentChange":115,"priceChange":12840,"timeAdded":1594130405982,"timeUpdated":1599746402721,"timeLastSeen":1600092003147,"dateAdded":"07-07-2020","dateUpdated":"10-09-2020","itemLink":"https://www.nabava.net/procesori/intel-core-i7-6700-34ghz-socket-1151-procesor-cijena-16855111"},{"itemID":"17197231","itemInfo":"Intel Core i5-6500T 2.5Ghz Socket 1151 procesor","itemPrice":1910,"itemStartPrice":1910,"percentChange":0,"priceChange":0,"timeAdded":1599746402721,"timeUpdated":1599746402721,"timeLastSeen":1600092003147,"dateAdded":"10-09-2020","dateUpdated":"10-09-2020","itemLink":"https://www.nabava.net/procesori/intel-core-i5-6500t-25ghz-socket-1151-procesor-cijena-17197231"},{"itemID":"17357871","itemInfo":"Intel Pentium G4500 3.5Ghz Socket 1151 procesor","itemPrice":757,"itemStartPrice":756,"percentChange":1,"priceChange":1,"timeAdded":1598882402591,"timeUpdated":1598882402591,"timeLastSeen":1600092003147,"dateAdded":"31-08-2020","dateUpdated":"14-09-2020","itemLink":"https://www.nabava.net/procesori/intel-pentium-g4500-35ghz-socket-1151-procesor-cijena-17357871"},{"itemID":"17532641","itemInfo":"Intel Pentium G4400 3.3Ghz Socket 1151 procesor","itemPrice":599,"itemStartPrice":599,"percentChange":0,"priceChange":0,"timeAdded":1594044003181,"timeUpdated":1594821614229,"timeLastSeen":1600092003147,"dateAdded":"06-07-2020","dateUpdated":"15-07-2020","itemLink":"https://www.nabava.net/procesori/intel-pentium-g4400-33ghz-socket-1151-procesor-cijena-17532641"},{"itemID":"18037931","itemInfo":"Intel Pentium G4400T 2.9Ghz Socket 1151 procesor","itemPrice":619,"itemStartPrice":619,"percentChange":0,"priceChange":0,"timeAdded":1599919204013,"timeUpdated":1599919204013,"timeLastSeen":1600092003147,"dateAdded":"12-09-2020","dateUpdated":"12-09-2020","itemLink":"https://www.nabava.net/procesori/intel-pentium-g4400t-29ghz-socket-1151-procesor-cijena-18037931"},{"itemID":"18037991","itemInfo":"Intel Core i3-6320 3.9Ghz Socket 1151 procesor","itemPrice":1200,"itemStartPrice":1200,"percentChange":0,"priceChange":0,"timeAdded":1596895203307,"timeUpdated":1596895203307,"timeLastSeen":1600092003147,"dateAdded":"08-08-2020","dateUpdated":"04-09-2020","itemLink":"https://www.nabava.net/procesori/intel-core-i3-6320-39ghz-socket-1151-procesor-cijena-18037991"},{"itemID":"23169041","itemInfo":"Intel Core i7-6800K 3.4Ghz Socket 2011 procesor","itemPrice":1864,"itemStartPrice":1938,"percentChange":-4,"priceChange":-74,"timeAdded":1594044003181,"timeUpdated":1598623204889,"timeLastSeen":1600092003147,"dateAdded":"06-07-2020","dateUpdated":"11-09-2020","itemLink":"https://www.nabava.net/procesori/intel-core-i7-6800k-34ghz-socket-2011-procesor-cijena-23169041"},{"itemID":"35550251","itemInfo":"Intel Core i5-7500 3.4Ghz Socket 1151 procesor","itemPrice":1620,"itemStartPrice":1840,"percentChange":-12,"priceChange":-220,"timeAdded":1599573603320,"timeUpdated":1599832803853,"timeLastSeen":1600092003147,"dateAdded":"08-09-2020","dateUpdated":"11-09-2020","itemLink":"https://www.nabava.net/procesori/intel-core-i5-7500-34ghz-socket-1151-procesor-cijena-35550251"},{"itemID":"35550271","itemInfo":"Intel Core i7-7700K 4.2Ghz Socket 1151 procesor","itemPrice":3938,"itemStartPrice":3938,"percentChange":0,"priceChange":0,"timeAdded":1594044003181,"timeUpdated":1594044003181,"timeLastSeen":1600092003147,"dateAdded":"06-07-2020","dateUpdated":"06-07-2020","itemLink":"https://www.nabava.net/procesori/intel-core-i7-7700k-42ghz-socket-1151-procesor-cijena-35550271"},{"itemID":"35571931","itemInfo":"Intel Core i3-7100 3.9Ghz Socket 1151 procesor","itemPrice":874,"itemStartPrice":595,"percentChange":47,"priceChange":279,"timeAdded":1594044003181,"timeUpdated":1599660003647,"timeLastSeen":1600092003147,"dateAdded":"06-07-2020","dateUpdated":"11-09-2020","itemLink":"https://www.nabava.net/procesori/intel-core-i3-7100-39ghz-socket-1151-procesor-cijena-35571931"},{"itemID":"35571951","itemInfo":"Intel Core i7-7700 3.6Ghz Socket 1151 procesor","itemPrice":2730,"itemStartPrice":2542,"percentChange":8,"priceChange":188,"timeAdded":1594044003181,"timeUpdated":1599573603320,"timeLastSeen":1600092003147,"dateAdded":"06-07-2020","dateUpdated":"12-09-2020","itemLink":"https://www.nabava.net/procesori/intel-core-i7-7700-36ghz-socket-1151-procesor-cijena-35571951"},{"itemID":"35817951","itemInfo":"Intel Core i3-7350K 4.2Ghz Socket 1151 procesor","itemPrice":2190,"itemStartPrice":1064,"percentChange":106,"priceChange":1126,"timeAdded":1594044003181,"timeUpdated":1597992838225,"timeLastSeen":1600092003147,"dateAdded":"06-07-2020","dateUpdated":"23-08-2020","itemLink":"https://www.nabava.net/procesori/intel-core-i3-7350k-42ghz-socket-1151-procesor-cijena-35817951"},{"itemID":"35829791","itemInfo":"Intel Celeron G3930 2.9Ghz Socket 1151 procesor","itemPrice":329,"itemStartPrice":329,"percentChange":0,"priceChange":0,"timeAdded":1598882402591,"timeUpdated":1600092003147,"timeLastSeen":1600092003147,"dateAdded":"31-08-2020","dateUpdated":"14-09-2020","itemLink":"https://www.nabava.net/procesori/intel-celeron-g3930-29ghz-socket-1151-procesor-cijena-35829791"},{"itemID":"36229311","itemInfo":"Intel Pentium G4560 3.5Ghz Socket 1151 procesor","itemPrice":525,"itemStartPrice":609,"percentChange":-14,"priceChange":-84,"timeAdded":1594821614229,"timeUpdated":1597672803971,"timeLastSeen":1600092003147,"dateAdded":"15-07-2020","dateUpdated":"10-09-2020","itemLink":"https://www.nabava.net/procesori/intel-pentium-g4560-35ghz-socket-1151-procesor-cijena-36229311"},{"itemID":"39114191","itemInfo":"AMD Ryzen 7 1800X 3.6Ghz Socket AM4 procesor","itemPrice":2069,"itemStartPrice":2069,"percentChange":0,"priceChange":0,"timeAdded":1594044003181,"timeUpdated":1594130405982,"timeLastSeen":1600092003147,"dateAdded":"06-07-2020","dateUpdated":"07-07-2020","itemLink":"https://www.nabava.net/procesori/amd-ryzen-7-1800x-36ghz-socket-am4-procesor-cijena-39114191"},{"itemID":"39114211","itemInfo":"AMD Ryzen 7 1700 3.0Ghz Socket AM4 procesor","itemPrice":1338,"itemStartPrice":1338,"percentChange":0,"priceChange":0,"timeAdded":1594044003181,"timeUpdated":1596463203810,"timeLastSeen":1600092003147,"dateAdded":"06-07-2020","dateUpdated":"03-08-2020","itemLink":"https://www.nabava.net/procesori/amd-ryzen-7-1700-30ghz-socket-am4-procesor-cijena-39114211"},{"itemID":"41853391","itemInfo":"AMD Ryzen 5 1400 3.2Ghz Socket AM4 procesor","itemPrice":1299,"itemStartPrice":1299,"percentChange":0,"priceChange":0,"timeAdded":1597845603407,"timeUpdated":1597845603407,"timeLastSeen":1600092003147,"dateAdded":"19-08-2020","dateUpdated":"19-08-2020","itemLink":"https://www.nabava.net/procesori/amd-ryzen-5-1400-32ghz-socket-am4-procesor-cijena-41853391"},{"itemID":"41853411","itemInfo":"AMD Ryzen 5 1600 3.2Ghz Socket AM4 procesor","itemPrice":859,"itemStartPrice":859,"percentChange":0,"priceChange":0,"timeAdded":1594044003181,"timeUpdated":1594044003181,"timeLastSeen":1600092003147,"dateAdded":"06-07-2020","dateUpdated":"03-09-2020","itemLink":"https://www.nabava.net/procesori/amd-ryzen-5-1600-32ghz-socket-am4-procesor-cijena-41853411"},{"itemID":"41853431","itemInfo":"AMD Ryzen 5 1600X 3.6Ghz Socket AM4 procesor","itemPrice":1642,"itemStartPrice":1642,"percentChange":0,"priceChange":0,"timeAdded":1594044003181,"timeUpdated":1594044003181,"timeLastSeen":1600092003147,"dateAdded":"06-07-2020","dateUpdated":"06-07-2020","itemLink":"https://www.nabava.net/procesori/amd-ryzen-5-1600x-36ghz-socket-am4-procesor-cijena-41853431"},{"itemID":"44319891","itemInfo":"Intel Core i7-7820X 3.6Ghz Socket 2066 procesor","itemPrice":5068,"itemStartPrice":5068,"percentChange":0,"priceChange":0,"timeAdded":1594044003181,"timeUpdated":1594044003181,"timeLastSeen":1600092003147,"dateAdded":"06-07-2020","dateUpdated":"09-09-2020","itemLink":"https://www.nabava.net/procesori/intel-core-i7-7820x-36ghz-socket-2066-procesor-cijena-44319891"},{"itemID":"44525091","itemInfo":"Intel Core i5-7640X 4.0Ghz Socket 2066 procesor","itemPrice":980,"itemStartPrice":980,"percentChange":0,"priceChange":0,"timeAdded":1594044003181,"timeUpdated":1594044003181,"timeLastSeen":1600092003147,"dateAdded":"06-07-2020","dateUpdated":"06-07-2020","itemLink":"https://www.nabava.net/procesori/intel-core-i5-7640x-40ghz-socket-2066-procesor-cijena-44525091"},{"itemID":"45740151","itemInfo":"AMD A6-9500 3.5Ghz Socket AM4 procesor","itemPrice":329,"itemStartPrice":329,"percentChange":0,"priceChange":0,"timeAdded":1594044003181,"timeUpdated":1596290402893,"timeLastSeen":1600092003147,"dateAdded":"06-07-2020","dateUpdated":"29-08-2020","itemLink":"https://www.nabava.net/procesori/amd-a6-9500-35ghz-socket-am4-procesor-cijena-45740151"},{"itemID":"45951171","itemInfo":"AMD Ryzen 3 1200 3.1Ghz Socket AM4 procesor","itemPrice":450,"itemStartPrice":450,"percentChange":0,"priceChange":0,"timeAdded":1600092003147,"timeUpdated":1600092003147,"timeLastSeen":1600092003147,"dateAdded":"14-09-2020","dateUpdated":"14-09-2020","itemLink":"https://www.nabava.net/procesori/amd-ryzen-3-1200-31ghz-socket-am4-procesor-cijena-45951171"},{"itemID":"45951191","itemInfo":"AMD Ryzen Threadripper 1920X 3.5Ghz Socket TR4 procesor","itemPrice":1746,"itemStartPrice":1746,"percentChange":0,"priceChange":0,"timeAdded":1594044003181,"timeUpdated":1596549603009,"timeLastSeen":1599832803853,"dateAdded":"06-07-2020","dateUpdated":"25-08-2020","itemLink":"https://www.nabava.net/procesori/amd-ryzen-threadripper-1920x-35ghz-socket-tr4-procesor-cijena-45951191"},{"itemID":"45951231","itemInfo":"AMD Ryzen 3 1300X 3.5Ghz Socket AM4 procesor","itemPrice":1130,"itemStartPrice":1130,"percentChange":0,"priceChange":0,"timeAdded":1594044003181,"timeUpdated":1597413603851,"timeLastSeen":1600092003147,"dateAdded":"06-07-2020","dateUpdated":"13-09-2020","itemLink":"https://www.nabava.net/procesori/amd-ryzen-3-1300x-35ghz-socket-am4-procesor-cijena-45951231"},{"itemID":"45951251","itemInfo":"AMD Ryzen Threadripper 1950X 3.4Ghz Socket TR4 procesor","itemPrice":6295,"itemStartPrice":6295,"percentChange":0,"priceChange":0,"timeAdded":1594044003181,"timeUpdated":1594044003181,"timeLastSeen":1600092003147,"dateAdded":"06-07-2020","dateUpdated":"10-09-2020","itemLink":"https://www.nabava.net/procesori/amd-ryzen-threadripper-1950x-34ghz-socket-tr4-procesor-cijena-45951251"},{"itemID":"45951291","itemInfo":"Intel Core i9-7900X 3.3Ghz Socket 2066 procesor","itemPrice":8299,"itemStartPrice":8299,"percentChange":0,"priceChange":0,"timeAdded":1594044003181,"timeUpdated":1594044003181,"timeLastSeen":1600092003147,"dateAdded":"06-07-2020","dateUpdated":"10-09-2020","itemLink":"https://www.nabava.net/procesori/intel-core-i9-7900x-33ghz-socket-2066-procesor-cijena-45951291"},{"itemID":"46822991","itemInfo":"Intel Xeon 5120 2.2Ghz Socket 771 procesor","itemPrice":13065,"itemStartPrice":13065,"percentChange":0,"priceChange":0,"timeAdded":1594044003181,"timeUpdated":1594044003181,"timeLastSeen":1600092003147,"dateAdded":"06-07-2020","dateUpdated":"14-09-2020","itemLink":"https://www.nabava.net/procesori/intel-xeon-5120-22ghz-socket-771-procesor-cijena-46822991"},{"itemID":"48597231","itemInfo":"Intel Xeon Silver 4110 2.1Ghz Socket 3647 procesor","itemPrice":3307,"itemStartPrice":3704,"percentChange":-11,"priceChange":-397,"timeAdded":1594044003181,"timeUpdated":1600092003147,"timeLastSeen":1600092003147,"dateAdded":"06-07-2020","dateUpdated":"14-09-2020","itemLink":"https://www.nabava.net/procesori/intel-xeon-silver-4110-21ghz-socket-3647-procesor-cijena-48597231"},{"itemID":"48723171","itemInfo":"Intel Core i3-8350K 4.0Ghz Socket 1151 procesor","itemPrice":1163,"itemStartPrice":1230,"percentChange":-6,"priceChange":-67,"timeAdded":1594044003181,"timeUpdated":1598364003379,"timeLastSeen":1600092003147,"dateAdded":"06-07-2020","dateUpdated":"10-09-2020","itemLink":"https://www.nabava.net/procesori/intel-core-i3-8350k-40ghz-socket-1151-procesor-cijena-48723171"},{"itemID":"48723191","itemInfo":"Intel Core i5-8600K 3.6Ghz Socket 1151 procesor","itemPrice":1675,"itemStartPrice":1675,"percentChange":0,"priceChange":0,"timeAdded":1594044003181,"timeUpdated":1596463203810,"timeLastSeen":1600092003147,"dateAdded":"06-07-2020","dateUpdated":"09-09-2020","itemLink":"https://www.nabava.net/procesori/intel-core-i5-8600k-36ghz-socket-1151-procesor-cijena-48723191"},{"itemID":"49069071","itemInfo":"AMD A12-9800E 3.1Ghz Socket AM4 procesor","itemPrice":790,"itemStartPrice":790,"percentChange":0,"priceChange":0,"timeAdded":1594044003181,"timeUpdated":1594044003181,"timeLastSeen":1600092003147,"dateAdded":"06-07-2020","dateUpdated":"06-07-2020","itemLink":"https://www.nabava.net/procesori/amd-a12-9800e-31ghz-socket-am4-procesor-cijena-49069071"},{"itemID":"49069091","itemInfo":"AMD Ryzen Threadripper 1900X 3.8Ghz Socket TR4 procesor","itemPrice":1016,"itemStartPrice":1041,"percentChange":-3,"priceChange":-25,"timeAdded":1594044003181,"timeUpdated":1600005603348,"timeLastSeen":1600092003147,"dateAdded":"06-07-2020","dateUpdated":"14-09-2020","itemLink":"https://www.nabava.net/procesori/amd-ryzen-threadripper-1900x-38ghz-socket-tr4-procesor-cijena-49069091"},{"itemID":"49069191","itemInfo":"Intel Core i9-7920X 2.9Ghz Socket 2066 procesor","itemPrice":5499,"itemStartPrice":5994,"percentChange":-9,"priceChange":-495,"timeAdded":1594044003181,"timeUpdated":1599660003647,"timeLastSeen":1600092003147,"dateAdded":"06-07-2020","dateUpdated":"09-09-2020","itemLink":"https://www.nabava.net/procesori/intel-core-i9-7920x-29ghz-socket-2066-procesor-cijena-49069191"},{"itemID":"49069231","itemInfo":"Intel Core i9-7940X 3.1Ghz Socket 2066 procesor","itemPrice":9356,"itemStartPrice":9262,"percentChange":2,"priceChange":94,"timeAdded":1598548716784,"timeUpdated":1598548716784,"timeLastSeen":1600092003147,"dateAdded":"27-08-2020","dateUpdated":"10-09-2020","itemLink":"https://www.nabava.net/procesori/intel-core-i9-7940x-31ghz-socket-2066-procesor-cijena-49069231"},{"itemID":"49069271","itemInfo":"Intel Core i9-7960X 2.8Ghz Socket 2066 procesor","itemPrice":5104,"itemStartPrice":5104,"percentChange":0,"priceChange":0,"timeAdded":1594044003181,"timeUpdated":1594044003181,"timeLastSeen":1600092003147,"dateAdded":"06-07-2020","dateUpdated":"10-09-2020","itemLink":"https://www.nabava.net/procesori/intel-core-i9-7960x-28ghz-socket-2066-procesor-cijena-49069271"},{"itemID":"49069291","itemInfo":"Intel Core i9-7980XE 2.6Ghz Socket 2066 procesor","itemPrice":17480,"itemStartPrice":17480,"percentChange":0,"priceChange":0,"timeAdded":1594044003181,"timeUpdated":1594044003181,"timeLastSeen":1600092003147,"dateAdded":"06-07-2020","dateUpdated":"06-07-2020","itemLink":"https://www.nabava.net/procesori/intel-core-i9-7980xe-26ghz-socket-2066-procesor-cijena-49069291"},{"itemID":"50199191","itemInfo":"Intel Core i3-8100 3.6Ghz Socket 1151 procesor","itemPrice":744,"itemStartPrice":744,"percentChange":0,"priceChange":0,"timeAdded":1594044003181,"timeUpdated":1594044003181,"timeLastSeen":1600092003147,"dateAdded":"06-07-2020","dateUpdated":"14-09-2020","itemLink":"https://www.nabava.net/procesori/intel-core-i3-8100-36ghz-socket-1151-procesor-cijena-50199191"},{"itemID":"50284291","itemInfo":"Intel Core i7-8700 3.2Ghz Socket 1151 procesor","itemPrice":2366,"itemStartPrice":2366,"percentChange":0,"priceChange":0,"timeAdded":1594044003181,"timeUpdated":1596549603009,"timeLastSeen":1600092003147,"dateAdded":"06-07-2020","dateUpdated":"14-09-2020","itemLink":"https://www.nabava.net/procesori/intel-core-i7-8700-32ghz-socket-1151-procesor-cijena-50284291"},{"itemID":"50320531","itemInfo":"Intel Core i7-8700K 3.7Ghz Socket 1151 procesor","itemPrice":3235,"itemStartPrice":3235,"percentChange":0,"priceChange":0,"timeAdded":1594044003181,"timeUpdated":1594044003181,"timeLastSeen":1600092003147,"dateAdded":"06-07-2020","dateUpdated":"14-09-2020","itemLink":"https://www.nabava.net/procesori/intel-core-i7-8700k-37ghz-socket-1151-procesor-cijena-50320531"},{"itemID":"50653211","itemInfo":"Intel Core i5-8400 2.8Ghz Socket 1151 procesor","itemPrice":1382,"itemStartPrice":1382,"percentChange":0,"priceChange":0,"timeAdded":1594044003181,"timeUpdated":1596031203407,"timeLastSeen":1600092003147,"dateAdded":"06-07-2020","dateUpdated":"14-09-2020","itemLink":"https://www.nabava.net/procesori/intel-core-i5-8400-28ghz-socket-1151-procesor-cijena-50653211"},{"itemID":"53895851","itemInfo":"AMD Athlon II X4 950 3.5Ghz Socket AM4 procesor","itemPrice":288,"itemStartPrice":288,"percentChange":0,"priceChange":0,"timeAdded":1596463203810,"timeUpdated":1596463203810,"timeLastSeen":1600092003147,"dateAdded":"03-08-2020","dateUpdated":"03-08-2020","itemLink":"https://www.nabava.net/procesori/amd-athlon-ii-x4-950-35ghz-socket-am4-procesor-cijena-53895851"},{"itemID":"59347131","itemInfo":"Intel Core i5-8500 3.0Ghz Socket 1151 procesor","itemPrice":1567,"itemStartPrice":1567,"percentChange":0,"priceChange":0,"timeAdded":1594044003181,"timeUpdated":1596549603009,"timeLastSeen":1600092003147,"dateAdded":"06-07-2020","dateUpdated":"14-09-2020","itemLink":"https://www.nabava.net/procesori/intel-core-i5-8500-30ghz-socket-1151-procesor-cijena-59347131"},{"itemID":"59347151","itemInfo":"Intel Pentium G5500 3.8Ghz Socket 1151 procesor","itemPrice":621,"itemStartPrice":621,"percentChange":0,"priceChange":0,"timeAdded":1594044003181,"timeUpdated":1594044003181,"timeLastSeen":1600092003147,"dateAdded":"06-07-2020","dateUpdated":"14-09-2020","itemLink":"https://www.nabava.net/procesori/intel-pentium-g5500-38ghz-socket-1151-procesor-cijena-59347151"},{"itemID":"59347171","itemInfo":"Intel Core i3-8300 3.7Ghz Socket 1151 procesor","itemPrice":944,"itemStartPrice":996,"percentChange":-6,"priceChange":-52,"timeAdded":1594044003181,"timeUpdated":1599660003647,"timeLastSeen":1600092003147,"dateAdded":"06-07-2020","dateUpdated":"14-09-2020","itemLink":"https://www.nabava.net/procesori/intel-core-i3-8300-37ghz-socket-1151-procesor-cijena-59347171"},{"itemID":"59705891","itemInfo":"Intel Core i5-8600 3.1Ghz Socket 1151 procesor","itemPrice":2060,"itemStartPrice":2070,"percentChange":-1,"priceChange":-10,"timeAdded":1594821614229,"timeUpdated":1599832803853,"timeLastSeen":1600092003147,"dateAdded":"15-07-2020","dateUpdated":"11-09-2020","itemLink":"https://www.nabava.net/procesori/intel-core-i5-8600-31ghz-socket-1151-procesor-cijena-59705891"},{"itemID":"59996371","itemInfo":"Intel Xeon Bronze 3104 1.7Ghz Socket 3647 procesor","itemPrice":1881,"itemStartPrice":1878,"percentChange":1,"priceChange":3,"timeAdded":1599487203813,"timeUpdated":1599487203813,"timeLastSeen":1599832803853,"dateAdded":"07-09-2020","dateUpdated":"10-09-2020","itemLink":"https://www.nabava.net/procesori/intel-xeon-bronze-3104-17ghz-socket-3647-procesor-cijena-59996371"},{"itemID":"59996411","itemInfo":"Intel Xeon Bronze 3106 1.7Ghz Socket 3647 procesor","itemPrice":2649,"itemStartPrice":2649,"percentChange":0,"priceChange":0,"timeAdded":1597992838225,"timeUpdated":1597992838225,"timeLastSeen":1600092003147,"dateAdded":"21-08-2020","dateUpdated":"21-08-2020","itemLink":"https://www.nabava.net/procesori/intel-xeon-bronze-3106-17ghz-socket-3647-procesor-cijena-59996411"},{"itemID":"59996431","itemInfo":"Intel Xeon Silver 4108 1.8Ghz Socket 3647 procesor","itemPrice":3599,"itemStartPrice":3599,"percentChange":0,"priceChange":0,"timeAdded":1594044003181,"timeUpdated":1594044003181,"timeLastSeen":1600092003147,"dateAdded":"06-07-2020","dateUpdated":"08-09-2020","itemLink":"https://www.nabava.net/procesori/intel-xeon-silver-4108-18ghz-socket-3647-procesor-cijena-59996431"},{"itemID":"59996451","itemInfo":"Intel Xeon Silver 4112 2.6Ghz Socket 3647 procesor","itemPrice":4017,"itemStartPrice":4017,"percentChange":0,"priceChange":0,"timeAdded":1594044003181,"timeUpdated":1594044003181,"timeLastSeen":1600092003147,"dateAdded":"06-07-2020","dateUpdated":"14-09-2020","itemLink":"https://www.nabava.net/procesori/intel-xeon-silver-4112-26ghz-socket-3647-procesor-cijena-59996451"},{"itemID":"59996491","itemInfo":"Intel Xeon Silver 4114 2.2Ghz Socket 3647 procesor","itemPrice":4885,"itemStartPrice":4885,"percentChange":0,"priceChange":0,"timeAdded":1594044003181,"timeUpdated":1597240805371,"timeLastSeen":1600092003147,"dateAdded":"06-07-2020","dateUpdated":"14-09-2020","itemLink":"https://www.nabava.net/procesori/intel-xeon-silver-4114-22ghz-socket-3647-procesor-cijena-59996491"},{"itemID":"59996571","itemInfo":"Intel Xeon Gold 6134 3.2Ghz Socket 3647 procesor","itemPrice":18604,"itemStartPrice":18604,"percentChange":0,"priceChange":0,"timeAdded":1594044003181,"timeUpdated":1594044003181,"timeLastSeen":1600092003147,"dateAdded":"06-07-2020","dateUpdated":"14-09-2020","itemLink":"https://www.nabava.net/procesori/intel-xeon-gold-6134-32ghz-socket-3647-procesor-cijena-59996571"},{"itemID":"60743631","itemInfo":"Intel Celeron G4900 3.1Ghz Socket 1151 procesor","itemPrice":291,"itemStartPrice":291,"percentChange":0,"priceChange":0,"timeAdded":1594044003181,"timeUpdated":1594044003181,"timeLastSeen":1600092003147,"dateAdded":"06-07-2020","dateUpdated":"03-09-2020","itemLink":"https://www.nabava.net/procesori/intel-celeron-g4900-31ghz-socket-1151-procesor-cijena-60743631"},{"itemID":"60743651","itemInfo":"Intel Pentium G5400 3.7Ghz Socket 1151 procesor","itemPrice":419,"itemStartPrice":464,"percentChange":-10,"priceChange":-45,"timeAdded":1594044003181,"timeUpdated":1599228003934,"timeLastSeen":1600092003147,"dateAdded":"06-07-2020","dateUpdated":"14-09-2020","itemLink":"https://www.nabava.net/procesori/intel-pentium-g5400-37ghz-socket-1151-procesor-cijena-60743651"},{"itemID":"60761971","itemInfo":"Intel Celeron G4920 3.2Ghz Socket 1151 procesor","itemPrice":236,"itemStartPrice":330,"percentChange":-29,"priceChange":-94,"timeAdded":1594044003181,"timeUpdated":1599832803853,"timeLastSeen":1600092003147,"dateAdded":"06-07-2020","dateUpdated":"11-09-2020","itemLink":"https://www.nabava.net/procesori/intel-celeron-g4920-32ghz-socket-1151-procesor-cijena-60761971"},{"itemID":"60761991","itemInfo":"Intel Pentium G5600 3.9Ghz Socket 1151 procesor","itemPrice":684,"itemStartPrice":630,"percentChange":9,"priceChange":54,"timeAdded":1594044003181,"timeUpdated":1599746402721,"timeLastSeen":1600092003147,"dateAdded":"06-07-2020","dateUpdated":"10-09-2020","itemLink":"https://www.nabava.net/procesori/intel-pentium-g5600-39ghz-socket-1151-procesor-cijena-60761991"},{"itemID":"60960751","itemInfo":"Intel Core i3-8100T 3.1Ghz Socket 1151 procesor","itemPrice":1349,"itemStartPrice":1349,"percentChange":0,"priceChange":0,"timeAdded":1597992838225,"timeUpdated":1597992838225,"timeLastSeen":1600092003147,"dateAdded":"21-08-2020","dateUpdated":"21-08-2020","itemLink":"https://www.nabava.net/procesori/intel-core-i3-8100t-31ghz-socket-1151-procesor-cijena-60960751"},{"itemID":"60960791","itemInfo":"Intel Core i5-8400T 1.7Ghz Socket 1151 procesor","itemPrice":2149,"itemStartPrice":2149,"percentChange":0,"priceChange":0,"timeAdded":1598882402591,"timeUpdated":1598882402591,"timeLastSeen":1600092003147,"dateAdded":"31-08-2020","dateUpdated":"31-08-2020","itemLink":"https://www.nabava.net/procesori/intel-core-i5-8400t-17ghz-socket-1151-procesor-cijena-60960791"},{"itemID":"61928791","itemInfo":"AMD Ryzen 7 2700 3.2Ghz Socket AM4 procesor","itemPrice":1299,"itemStartPrice":1299,"percentChange":0,"priceChange":0,"timeAdded":1594044003181,"timeUpdated":1594044003181,"timeLastSeen":1600092003147,"dateAdded":"06-07-2020","dateUpdated":"06-07-2020","itemLink":"https://www.nabava.net/procesori/amd-ryzen-7-2700-32ghz-socket-am4-procesor-cijena-61928791"},{"itemID":"61928811","itemInfo":"AMD Ryzen 3 2200G 3.5Ghz Socket AM4 procesor","itemPrice":921,"itemStartPrice":919,"percentChange":1,"priceChange":2,"timeAdded":1594044003181,"timeUpdated":1599832803853,"timeLastSeen":1600092003147,"dateAdded":"06-07-2020","dateUpdated":"14-09-2020","itemLink":"https://www.nabava.net/procesori/amd-ryzen-3-2200g-35ghz-socket-am4-procesor-cijena-61928811"},{"itemID":"61928831","itemInfo":"AMD Ryzen 5 2400G 3.6Ghz Socket AM4 procesor","itemPrice":1099,"itemStartPrice":1099,"percentChange":0,"priceChange":0,"timeAdded":1594044003181,"timeUpdated":1594044003181,"timeLastSeen":1600092003147,"dateAdded":"06-07-2020","dateUpdated":"06-07-2020","itemLink":"https://www.nabava.net/procesori/amd-ryzen-5-2400g-36ghz-socket-am4-procesor-cijena-61928831"},{"itemID":"61928851","itemInfo":"AMD Ryzen 7 2700X 3.7Ghz Socket AM4 procesor","itemPrice":1412,"itemStartPrice":1412,"percentChange":0,"priceChange":0,"timeAdded":1594044003181,"timeUpdated":1594044003181,"timeLastSeen":1600092003147,"dateAdded":"06-07-2020","dateUpdated":"14-09-2020","itemLink":"https://www.nabava.net/procesori/amd-ryzen-7-2700x-37ghz-socket-am4-procesor-cijena-61928851"},{"itemID":"61928871","itemInfo":"AMD Ryzen 5 2600 3.4Ghz Socket AM4 procesor","itemPrice":1045,"itemStartPrice":1139,"percentChange":-9,"priceChange":-94,"timeAdded":1594044003181,"timeUpdated":1598796004508,"timeLastSeen":1600092003147,"dateAdded":"06-07-2020","dateUpdated":"11-09-2020","itemLink":"https://www.nabava.net/procesori/amd-ryzen-5-2600-34ghz-socket-am4-procesor-cijena-61928871"},{"itemID":"61928891","itemInfo":"AMD Ryzen 5 2600X 3.6Ghz Socket AM4 procesor","itemPrice":1087,"itemStartPrice":1087,"percentChange":0,"priceChange":0,"timeAdded":1594044003181,"timeUpdated":1595944803203,"timeLastSeen":1600092003147,"dateAdded":"06-07-2020","dateUpdated":"14-09-2020","itemLink":"https://www.nabava.net/procesori/amd-ryzen-5-2600x-36ghz-socket-am4-procesor-cijena-61928891"},{"itemID":"62112951","itemInfo":"Intel Xeon Gold 5122 3.6Ghz Socket 3647 procesor","itemPrice":10260,"itemStartPrice":9661,"percentChange":7,"priceChange":599,"timeAdded":1594044003181,"timeUpdated":1599141603573,"timeLastSeen":1600092003147,"dateAdded":"06-07-2020","dateUpdated":"14-09-2020","itemLink":"https://www.nabava.net/procesori/intel-xeon-gold-5122-36ghz-socket-3647-procesor-cijena-62112951"},{"itemID":"62197511","itemInfo":"Intel Xeon E3-1220 v5 3.0Ghz Socket 1151 procesor","itemPrice":1899,"itemStartPrice":1899,"percentChange":0,"priceChange":0,"timeAdded":1597992838225,"timeUpdated":1597992838225,"timeLastSeen":1600092003147,"dateAdded":"21-08-2020","dateUpdated":"21-08-2020","itemLink":"https://www.nabava.net/procesori/intel-xeon-e3-1220-v5-30ghz-socket-1151-procesor-cijena-62197511"},{"itemID":"62197531","itemInfo":"Intel Xeon E3-1220 v6 3.0Ghz Socket 1151 procesor","itemPrice":1675,"itemStartPrice":1675,"percentChange":0,"priceChange":0,"timeAdded":1594044003181,"timeUpdated":1594044003181,"timeLastSeen":1600092003147,"dateAdded":"06-07-2020","dateUpdated":"14-09-2020","itemLink":"https://www.nabava.net/procesori/intel-xeon-e3-1220-v6-30ghz-socket-1151-procesor-cijena-62197531"},{"itemID":"62197551","itemInfo":"Intel Xeon E3-1240 v6 3.7Ghz Socket 1151 procesor","itemPrice":2199,"itemStartPrice":2199,"percentChange":0,"priceChange":0,"timeAdded":1594044003181,"timeUpdated":1594044003181,"timeLastSeen":1600092003147,"dateAdded":"06-07-2020","dateUpdated":"09-09-2020","itemLink":"https://www.nabava.net/procesori/intel-xeon-e3-1240-v6-37ghz-socket-1151-procesor-cijena-62197551"},{"itemID":"62197571","itemInfo":"Intel Xeon E3-1240 v5 3.5Ghz Socket 1151 procesor","itemPrice":2349,"itemStartPrice":2349,"percentChange":0,"priceChange":0,"timeAdded":1598018403613,"timeUpdated":1598018403613,"timeLastSeen":1600092003147,"dateAdded":"21-08-2020","dateUpdated":"21-08-2020","itemLink":"https://www.nabava.net/procesori/intel-xeon-e3-1240-v5-35ghz-socket-1151-procesor-cijena-62197571"},{"itemID":"62197591","itemInfo":"Intel Xeon E5-2620 v4 2.1Ghz Socket 2011 procesor","itemPrice":3507,"itemStartPrice":3401,"percentChange":4,"priceChange":106,"timeAdded":1594044003181,"timeUpdated":1598364003379,"timeLastSeen":1600092003147,"dateAdded":"06-07-2020","dateUpdated":"14-09-2020","itemLink":"https://www.nabava.net/procesori/intel-xeon-e5-2620-v4-21ghz-socket-2011-procesor-cijena-62197591"},{"itemID":"62197611","itemInfo":"Intel Xeon E5-2620 v3 2.4Ghz Socket 2011 procesor","itemPrice":3649,"itemStartPrice":3649,"percentChange":0,"priceChange":0,"timeAdded":1598882402591,"timeUpdated":1598882402591,"timeLastSeen":1600092003147,"dateAdded":"31-08-2020","dateUpdated":"31-08-2020","itemLink":"https://www.nabava.net/procesori/intel-xeon-e5-2620-v3-24ghz-socket-2011-procesor-cijena-62197611"},{"itemID":"62197631","itemInfo":"Intel Xeon E5-2603 v4 1.7Ghz Socket 2011 procesor","itemPrice":2199,"itemStartPrice":2199,"percentChange":0,"priceChange":0,"timeAdded":1598104803336,"timeUpdated":1598104803336,"timeLastSeen":1600092003147,"dateAdded":"22-08-2020","dateUpdated":"22-08-2020","itemLink":"https://www.nabava.net/procesori/intel-xeon-e5-2603-v4-17ghz-socket-2011-procesor-cijena-62197631"},{"itemID":"62197691","itemInfo":"Intel Xeon E5-2609 v4 1.7Ghz Socket 2011 procesor","itemPrice":3049,"itemStartPrice":3049,"percentChange":0,"priceChange":0,"timeAdded":1598882402591,"timeUpdated":1598882402591,"timeLastSeen":1600092003147,"dateAdded":"31-08-2020","dateUpdated":"31-08-2020","itemLink":"https://www.nabava.net/procesori/intel-xeon-e5-2609-v4-17ghz-socket-2011-procesor-cijena-62197691"},{"itemID":"62197751","itemInfo":"Intel Xeon E5-1650 v4 3.6Ghz Socket 2011 procesor","itemPrice":5799,"itemStartPrice":5799,"percentChange":0,"priceChange":0,"timeAdded":1597992838225,"timeUpdated":1599314403619,"timeLastSeen":1600092003147,"dateAdded":"21-08-2020","dateUpdated":"05-09-2020","itemLink":"https://www.nabava.net/procesori/intel-xeon-e5-1650-v4-36ghz-socket-2011-procesor-cijena-62197751"},{"itemID":"62197811","itemInfo":"Intel Xeon E5-2650 v4 2.2Ghz Socket 2011 procesor","itemPrice":9708,"itemStartPrice":9708,"percentChange":0,"priceChange":0,"timeAdded":1594044003181,"timeUpdated":1594044003181,"timeLastSeen":1600092003147,"dateAdded":"06-07-2020","dateUpdated":"14-09-2020","itemLink":"https://www.nabava.net/procesori/intel-xeon-e5-2650-v4-22ghz-socket-2011-procesor-cijena-62197811"},{"itemID":"62197851","itemInfo":"Intel Xeon E3-1230 v5 3.4Ghz Socket 1151 procesor","itemPrice":2199,"itemStartPrice":2199,"percentChange":0,"priceChange":0,"timeAdded":1597992838225,"timeUpdated":1597992838225,"timeLastSeen":1600092003147,"dateAdded":"21-08-2020","dateUpdated":"21-08-2020","itemLink":"https://www.nabava.net/procesori/intel-xeon-e3-1230-v5-34ghz-socket-1151-procesor-cijena-62197851"},{"itemID":"62197871","itemInfo":"Intel Xeon E3-1230 v6 3.5Ghz Socket 1151 procesor","itemPrice":2156,"itemStartPrice":2156,"percentChange":0,"priceChange":0,"timeAdded":1594044003181,"timeUpdated":1594044003181,"timeLastSeen":1600092003147,"dateAdded":"06-07-2020","dateUpdated":"14-09-2020","itemLink":"https://www.nabava.net/procesori/intel-xeon-e3-1230-v6-35ghz-socket-1151-procesor-cijena-62197871"},{"itemID":"62197911","itemInfo":"Intel Xeon E5-2640 v4 2.4Ghz Socket 2011 procesor","itemPrice":8199,"itemStartPrice":8199,"percentChange":0,"priceChange":0,"timeAdded":1594044003181,"timeUpdated":1594044003181,"timeLastSeen":1600092003147,"dateAdded":"06-07-2020","dateUpdated":"11-09-2020","itemLink":"https://www.nabava.net/procesori/intel-xeon-e5-2640-v4-24ghz-socket-2011-procesor-cijena-62197911"},{"itemID":"62197931","itemInfo":"Intel Xeon E5-2690 v4 2.6Ghz Socket 2011 procesor","itemPrice":18199,"itemStartPrice":18199,"percentChange":0,"priceChange":0,"timeAdded":1598882402591,"timeUpdated":1598882402591,"timeLastSeen":1600092003147,"dateAdded":"31-08-2020","dateUpdated":"31-08-2020","itemLink":"https://www.nabava.net/procesori/intel-xeon-e5-2690-v4-26ghz-socket-2011-procesor-cijena-62197931"},{"itemID":"62197991","itemInfo":"Intel Xeon E5-2660 v4 2.0Ghz Socket 2011 procesor","itemPrice":12139,"itemStartPrice":12091,"percentChange":1,"priceChange":48,"timeAdded":1597992838225,"timeUpdated":1597992838225,"timeLastSeen":1600092003147,"dateAdded":"21-08-2020","dateUpdated":"14-09-2020","itemLink":"https://www.nabava.net/procesori/intel-xeon-e5-2660-v4-20ghz-socket-2011-procesor-cijena-62197991"},{"itemID":"62198011","itemInfo":"Intel Xeon E5-2687W v4 3.0Ghz Socket 2011 procesor","itemPrice":21399,"itemStartPrice":21399,"percentChange":0,"priceChange":0,"timeAdded":1597992838225,"timeUpdated":1597992838225,"timeLastSeen":1600092003147,"dateAdded":"21-08-2020","dateUpdated":"21-08-2020","itemLink":"https://www.nabava.net/procesori/intel-xeon-e5-2687w-v4-30ghz-socket-2011-procesor-cijena-62198011"},{"itemID":"62198051","itemInfo":"Intel Xeon E5-2680 v4 2.4Ghz Socket 2011 procesor","itemPrice":14665,"itemStartPrice":14579,"percentChange":1,"priceChange":86,"timeAdded":1598882402591,"timeUpdated":1598882402591,"timeLastSeen":1600092003147,"dateAdded":"31-08-2020","dateUpdated":"14-09-2020","itemLink":"https://www.nabava.net/procesori/intel-xeon-e5-2680-v4-24ghz-socket-2011-procesor-cijena-62198051"},{"itemID":"62198091","itemInfo":"Intel Xeon E3-1270 v6 3.8Ghz Socket 1151 procesor","itemPrice":2849,"itemStartPrice":2849,"percentChange":0,"priceChange":0,"timeAdded":1598191203074,"timeUpdated":1598796004508,"timeLastSeen":1600092003147,"dateAdded":"23-08-2020","dateUpdated":"11-09-2020","itemLink":"https://www.nabava.net/procesori/intel-xeon-e3-1270-v6-38ghz-socket-1151-procesor-cijena-62198091"},{"itemID":"62198111","itemInfo":"Intel Xeon E3-1270 v5 3.6Ghz Socket 1151 procesor","itemPrice":2849,"itemStartPrice":2849,"percentChange":0,"priceChange":0,"timeAdded":1597992838225,"timeUpdated":1597992838225,"timeLastSeen":1600092003147,"dateAdded":"21-08-2020","dateUpdated":"21-08-2020","itemLink":"https://www.nabava.net/procesori/intel-xeon-e3-1270-v5-36ghz-socket-1151-procesor-cijena-62198111"},{"itemID":"62198131","itemInfo":"Intel Xeon E5-2630 v4 2.2Ghz Socket 2011 procesor","itemPrice":5799,"itemStartPrice":5799,"percentChange":0,"priceChange":0,"timeAdded":1594044003181,"timeUpdated":1594044003181,"timeLastSeen":1600092003147,"dateAdded":"06-07-2020","dateUpdated":"12-09-2020","itemLink":"https://www.nabava.net/procesori/intel-xeon-e5-2630-v4-22ghz-socket-2011-procesor-cijena-62198131"},{"itemID":"62198151","itemInfo":"Intel Xeon E5-1620 v4 3.5Ghz Socket 2011 procesor","itemPrice":2999,"itemStartPrice":2999,"percentChange":0,"priceChange":0,"timeAdded":1597992838225,"timeUpdated":1597992838225,"timeLastSeen":1600092003147,"dateAdded":"21-08-2020","dateUpdated":"21-08-2020","itemLink":"https://www.nabava.net/procesori/intel-xeon-e5-1620-v4-35ghz-socket-2011-procesor-cijena-62198151"},{"itemID":"62198231","itemInfo":"Intel Xeon E3-1225 v6 3.3Ghz Socket 1151 procesor","itemPrice":1789,"itemStartPrice":1789,"percentChange":0,"priceChange":0,"timeAdded":1594044003181,"timeUpdated":1594044003181,"timeLastSeen":1600092003147,"dateAdded":"06-07-2020","dateUpdated":"14-09-2020","itemLink":"https://www.nabava.net/procesori/intel-xeon-e3-1225-v6-33ghz-socket-1151-procesor-cijena-62198231"},{"itemID":"62198251","itemInfo":"Intel Xeon E5-2697 v4 2.3Ghz Socket 2011 procesor","itemPrice":22477,"itemStartPrice":22477,"percentChange":0,"priceChange":0,"timeAdded":1594044003181,"timeUpdated":1594044003181,"timeLastSeen":1600092003147,"dateAdded":"06-07-2020","dateUpdated":"14-09-2020","itemLink":"https://www.nabava.net/procesori/intel-xeon-e5-2697-v4-23ghz-socket-2011-procesor-cijena-62198251"},{"itemID":"62198291","itemInfo":"Intel Xeon E3-1275 v6 3.8Ghz Socket 1151 procesor","itemPrice":2860,"itemStartPrice":2940,"percentChange":-3,"priceChange":-80,"timeAdded":1594044003181,"timeUpdated":1599141603573,"timeLastSeen":1600092003147,"dateAdded":"06-07-2020","dateUpdated":"13-09-2020","itemLink":"https://www.nabava.net/procesori/intel-xeon-e3-1275-v6-38ghz-socket-1151-procesor-cijena-62198291"},{"itemID":"62198331","itemInfo":"Intel Xeon E3-1245 v6 3.7Ghz Socket 1151 procesor","itemPrice":2473,"itemStartPrice":2473,"percentChange":0,"priceChange":0,"timeAdded":1594044003181,"timeUpdated":1594044003181,"timeLastSeen":1600092003147,"dateAdded":"06-07-2020","dateUpdated":"14-09-2020","itemLink":"https://www.nabava.net/procesori/intel-xeon-e3-1245-v6-37ghz-socket-1151-procesor-cijena-62198331"},{"itemID":"62198371","itemInfo":"Intel Xeon E5-2699 v4 2.2Ghz Socket 2011 procesor","itemPrice":35849,"itemStartPrice":35849,"percentChange":0,"priceChange":0,"timeAdded":1597992838225,"timeUpdated":1597992838225,"timeLastSeen":1600092003147,"dateAdded":"21-08-2020","dateUpdated":"21-08-2020","itemLink":"https://www.nabava.net/procesori/intel-xeon-e5-2699-v4-22ghz-socket-2011-procesor-cijena-62198371"},{"itemID":"62198391","itemInfo":"Intel Xeon E5-2683 v4 2.1Ghz Socket 2011 procesor","itemPrice":16099,"itemStartPrice":16099,"percentChange":0,"priceChange":0,"timeAdded":1597992838225,"timeUpdated":1597992838225,"timeLastSeen":1600092003147,"dateAdded":"21-08-2020","dateUpdated":"21-08-2020","itemLink":"https://www.nabava.net/procesori/intel-xeon-e5-2683-v4-21ghz-socket-2011-procesor-cijena-62198391"},{"itemID":"62198411","itemInfo":"Intel Xeon E5-2667 v4 3.2Ghz Socket 2011 procesor","itemPrice":17282,"itemStartPrice":17282,"percentChange":0,"priceChange":0,"timeAdded":1594044003181,"timeUpdated":1594908003445,"timeLastSeen":1600092003147,"dateAdded":"06-07-2020","dateUpdated":"14-09-2020","itemLink":"https://www.nabava.net/procesori/intel-xeon-e5-2667-v4-32ghz-socket-2011-procesor-cijena-62198411"},{"itemID":"62198431","itemInfo":"Intel Xeon E5-2630L v4 1.8Ghz Socket 2011 procesor","itemPrice":5349,"itemStartPrice":5349,"percentChange":0,"priceChange":0,"timeAdded":1597992838225,"timeUpdated":1597992838225,"timeLastSeen":1600092003147,"dateAdded":"21-08-2020","dateUpdated":"21-08-2020","itemLink":"https://www.nabava.net/procesori/intel-xeon-e5-2630l-v4-18ghz-socket-2011-procesor-cijena-62198431"},{"itemID":"62198451","itemInfo":"Intel Xeon E3-1260L v5 2.9Ghz Socket 1151 procesor","itemPrice":2999,"itemStartPrice":2999,"percentChange":0,"priceChange":0,"timeAdded":1598796004508,"timeUpdated":1598796004508,"timeLastSeen":1600092003147,"dateAdded":"30-08-2020","dateUpdated":"30-08-2020","itemLink":"https://www.nabava.net/procesori/intel-xeon-e3-1260l-v5-29ghz-socket-1151-procesor-cijena-62198451"},{"itemID":"62198471","itemInfo":"Intel Xeon E5-2623 v4 2.6Ghz Socket 2011 procesor","itemPrice":4499,"itemStartPrice":4499,"percentChange":0,"priceChange":0,"timeAdded":1597992838225,"timeUpdated":1597992838225,"timeLastSeen":1600092003147,"dateAdded":"21-08-2020","dateUpdated":"21-08-2020","itemLink":"https://www.nabava.net/procesori/intel-xeon-e5-2623-v4-26ghz-socket-2011-procesor-cijena-62198471"},{"itemID":"62198531","itemInfo":"Intel Xeon E5-2695 v4 2.1Ghz Socket 2011 procesor","itemPrice":20402,"itemStartPrice":20402,"percentChange":0,"priceChange":0,"timeAdded":1597500003018,"timeUpdated":1597500003018,"timeLastSeen":1600092003147,"dateAdded":"15-08-2020","dateUpdated":"14-09-2020","itemLink":"https://www.nabava.net/procesori/intel-xeon-e5-2695-v4-21ghz-socket-2011-procesor-cijena-62198531"},{"itemID":"62198551","itemInfo":"Intel Xeon E5-2697A v4 2.6Ghz Socket 2011 procesor","itemPrice":25149,"itemStartPrice":25149,"percentChange":0,"priceChange":0,"timeAdded":1597992838225,"timeUpdated":1597992838225,"timeLastSeen":1600092003147,"dateAdded":"21-08-2020","dateUpdated":"21-08-2020","itemLink":"https://www.nabava.net/procesori/intel-xeon-e5-2697a-v4-26ghz-socket-2011-procesor-cijena-62198551"},{"itemID":"62198571","itemInfo":"Intel Xeon E5-2698 v4 2.2Ghz Socket 2011 procesor","itemPrice":28099,"itemStartPrice":28099,"percentChange":0,"priceChange":0,"timeAdded":1597992838225,"timeUpdated":1597992838225,"timeLastSeen":1600092003147,"dateAdded":"21-08-2020","dateUpdated":"21-08-2020","itemLink":"https://www.nabava.net/procesori/intel-xeon-e5-2698-v4-22ghz-socket-2011-procesor-cijena-62198571"},{"itemID":"62246651","itemInfo":"Intel Xeon Silver 4116 2.1Ghz Socket 3647 procesor","itemPrice":7113,"itemStartPrice":7113,"percentChange":0,"priceChange":0,"timeAdded":1594044003181,"timeUpdated":1594044003181,"timeLastSeen":1600092003147,"dateAdded":"06-07-2020","dateUpdated":"14-09-2020","itemLink":"https://www.nabava.net/procesori/intel-xeon-silver-4116-21ghz-socket-3647-procesor-cijena-62246651"},{"itemID":"62246671","itemInfo":"Intel Xeon Gold 6148 2.4Ghz Socket 3647 procesor","itemPrice":24118,"itemStartPrice":24118,"percentChange":0,"priceChange":0,"timeAdded":1594044003181,"timeUpdated":1594044003181,"timeLastSeen":1600092003147,"dateAdded":"06-07-2020","dateUpdated":"14-09-2020","itemLink":"https://www.nabava.net/procesori/intel-xeon-gold-6148-24ghz-socket-3647-procesor-cijena-62246671"},{"itemID":"63124771","itemInfo":"Intel Xeon E5-2637 v4 3.5Ghz Socket 2011 procesor","itemPrice":8371,"itemStartPrice":8371,"percentChange":0,"priceChange":0,"timeAdded":1594044003181,"timeUpdated":1594044003181,"timeLastSeen":1600092003147,"dateAdded":"06-07-2020","dateUpdated":"14-09-2020","itemLink":"https://www.nabava.net/procesori/intel-xeon-e5-2637-v4-35ghz-socket-2011-procesor-cijena-63124771"},{"itemID":"63190071","itemInfo":"Intel Xeon Gold 6128 3.4Ghz Socket 3647 procesor","itemPrice":13229,"itemStartPrice":13229,"percentChange":0,"priceChange":0,"timeAdded":1594044003181,"timeUpdated":1594044003181,"timeLastSeen":1600092003147,"dateAdded":"06-07-2020","dateUpdated":"14-09-2020","itemLink":"https://www.nabava.net/procesori/intel-xeon-gold-6128-34ghz-socket-3647-procesor-cijena-63190071"},{"itemID":"63260691","itemInfo":"Intel Xeon E5-2650L v4 1.7Ghz Socket 2011 procesor","itemPrice":11168,"itemStartPrice":11168,"percentChange":0,"priceChange":0,"timeAdded":1594044003181,"timeUpdated":1594044003181,"timeLastSeen":1600092003147,"dateAdded":"06-07-2020","dateUpdated":"14-09-2020","itemLink":"https://www.nabava.net/procesori/intel-xeon-e5-2650l-v4-17ghz-socket-2011-procesor-cijena-63260691"},{"itemID":"63421191","itemInfo":"Intel Xeon E5-2660 2.2Ghz Socket 2011 procesor","itemPrice":12122,"itemStartPrice":12122,"percentChange":0,"priceChange":0,"timeAdded":1594044003181,"timeUpdated":1594044003181,"timeLastSeen":1600092003147,"dateAdded":"06-07-2020","dateUpdated":"14-09-2020","itemLink":"https://www.nabava.net/procesori/intel-xeon-e5-2660-22ghz-socket-2011-procesor-cijena-63421191"},{"itemID":"64726131","itemInfo":"AMD Epyc 7401 2.0Ghz Socket SP3 procesor","itemPrice":8671,"itemStartPrice":13321,"percentChange":-35,"priceChange":-4650,"timeAdded":1594044003181,"timeUpdated":1599573603320,"timeLastSeen":1600092003147,"dateAdded":"06-07-2020","dateUpdated":"14-09-2020","itemLink":"https://www.nabava.net/procesori/amd-epyc-7401-20ghz-socket-sp3-procesor-cijena-64726131"},{"itemID":"64726151","itemInfo":"AMD Epyc 7281 2.1Ghz Socket SP3 procesor","itemPrice":5993,"itemStartPrice":5993,"percentChange":0,"priceChange":0,"timeAdded":1594044003181,"timeUpdated":1595944803203,"timeLastSeen":1600092003147,"dateAdded":"06-07-2020","dateUpdated":"28-07-2020","itemLink":"https://www.nabava.net/procesori/amd-epyc-7281-21ghz-socket-sp3-procesor-cijena-64726151"},{"itemID":"64726171","itemInfo":"AMD Epyc 7351 2.4Ghz Socket SP3 procesor","itemPrice":9358,"itemStartPrice":6030,"percentChange":56,"priceChange":3328,"timeAdded":1594044003181,"timeUpdated":1597759203735,"timeLastSeen":1600092003147,"dateAdded":"06-07-2020","dateUpdated":"14-09-2020","itemLink":"https://www.nabava.net/procesori/amd-epyc-7351-24ghz-socket-sp3-procesor-cijena-64726171"},{"itemID":"64726191","itemInfo":"AMD Epyc 7301 2.2Ghz Socket SP3 procesor","itemPrice":4560,"itemStartPrice":7599,"percentChange":-40,"priceChange":-3039,"timeAdded":1598018403613,"timeUpdated":1599660003647,"timeLastSeen":1600092003147,"dateAdded":"21-08-2020","dateUpdated":"14-09-2020","itemLink":"https://www.nabava.net/procesori/amd-epyc-7301-22ghz-socket-sp3-procesor-cijena-64726191"},{"itemID":"64726211","itemInfo":"AMD Epyc 7451 2.3Ghz Socket SP3 procesor","itemPrice":9173,"itemStartPrice":11065,"percentChange":-18,"priceChange":-1892,"timeAdded":1594044003181,"timeUpdated":1598968803733,"timeLastSeen":1600092003147,"dateAdded":"06-07-2020","dateUpdated":"14-09-2020","itemLink":"https://www.nabava.net/procesori/amd-epyc-7451-23ghz-socket-sp3-procesor-cijena-64726211"},{"itemID":"64726231","itemInfo":"AMD Epyc 7501 2.0Ghz Socket SP3 procesor","itemPrice":31249,"itemStartPrice":28355,"percentChange":11,"priceChange":2894,"timeAdded":1594044003181,"timeUpdated":1599141603573,"timeLastSeen":1600092003147,"dateAdded":"06-07-2020","dateUpdated":"03-09-2020","itemLink":"https://www.nabava.net/procesori/amd-epyc-7501-20ghz-socket-sp3-procesor-cijena-64726231"},{"itemID":"64726251","itemInfo":"AMD Epyc 7601 2.2Ghz Socket SP3 procesor","itemPrice":23617,"itemStartPrice":37566,"percentChange":-38,"priceChange":-13949,"timeAdded":1594044003181,"timeUpdated":1599746402721,"timeLastSeen":1600092003147,"dateAdded":"06-07-2020","dateUpdated":"10-09-2020","itemLink":"https://www.nabava.net/procesori/amd-epyc-7601-22ghz-socket-sp3-procesor-cijena-64726251"},{"itemID":"64726271","itemInfo":"AMD Epyc 7551 2.0Ghz Socket SP3 procesor","itemPrice":9179,"itemStartPrice":9179,"percentChange":0,"priceChange":0,"timeAdded":1594044003181,"timeUpdated":1595167204818,"timeLastSeen":1600092003147,"dateAdded":"06-07-2020","dateUpdated":"14-09-2020","itemLink":"https://www.nabava.net/procesori/amd-epyc-7551-20ghz-socket-sp3-procesor-cijena-64726271"},{"itemID":"64726291","itemInfo":"AMD Epyc 7251 2.1Ghz Socket SP3 procesor","itemPrice":4399,"itemStartPrice":4399,"percentChange":0,"priceChange":0,"timeAdded":1594044003181,"timeUpdated":1595253604252,"timeLastSeen":1600092003147,"dateAdded":"06-07-2020","dateUpdated":"10-09-2020","itemLink":"https://www.nabava.net/procesori/amd-epyc-7251-21ghz-socket-sp3-procesor-cijena-64726291"},{"itemID":"64726311","itemInfo":"AMD Epyc 7401P 2.0Ghz Socket SP3 procesor","itemPrice":9711,"itemStartPrice":9343,"percentChange":4,"priceChange":368,"timeAdded":1594044003181,"timeUpdated":1597845603407,"timeLastSeen":1600092003147,"dateAdded":"06-07-2020","dateUpdated":"13-09-2020","itemLink":"https://www.nabava.net/procesori/amd-epyc-7401p-20ghz-socket-sp3-procesor-cijena-64726311"},{"itemID":"64726331","itemInfo":"AMD Epyc 7551P 2.0Ghz Socket SP3 procesor","itemPrice":9799,"itemStartPrice":18073,"percentChange":-46,"priceChange":-8274,"timeAdded":1594044003181,"timeUpdated":1599228003934,"timeLastSeen":1600092003147,"dateAdded":"06-07-2020","dateUpdated":"08-09-2020","itemLink":"https://www.nabava.net/procesori/amd-epyc-7551p-20ghz-socket-sp3-procesor-cijena-64726331"},{"itemID":"64726351","itemInfo":"AMD Epyc 7351P 2.4Ghz Socket SP3 procesor","itemPrice":4831,"itemStartPrice":4754,"percentChange":2,"priceChange":77,"timeAdded":1598018403613,"timeUpdated":1599746402721,"timeLastSeen":1600092003147,"dateAdded":"21-08-2020","dateUpdated":"14-09-2020","itemLink":"https://www.nabava.net/procesori/amd-epyc-7351p-24ghz-socket-sp3-procesor-cijena-64726351"},{"itemID":"66082551","itemInfo":"AMD Ryzen Threadripper 2990WX 3.0Ghz Socket TR4 procesor","itemPrice":14699,"itemStartPrice":14699,"percentChange":0,"priceChange":0,"timeAdded":1594044003181,"timeUpdated":1594044003181,"timeLastSeen":1600092003147,"dateAdded":"06-07-2020","dateUpdated":"14-09-2020","itemLink":"https://www.nabava.net/procesori/amd-ryzen-threadripper-2990wx-30ghz-socket-tr4-procesor-cijena-66082551"},{"itemID":"67956151","itemInfo":"Intel Core i5-9600K 3.7Ghz Socket 1151 procesor","itemPrice":1548,"itemStartPrice":1548,"percentChange":0,"priceChange":0,"timeAdded":1594044003181,"timeUpdated":1594044003181,"timeLastSeen":1600092003147,"dateAdded":"06-07-2020","dateUpdated":"14-09-2020","itemLink":"https://www.nabava.net/procesori/intel-core-i5-9600k-37ghz-socket-1151-procesor-cijena-67956151"},{"itemID":"68991051","itemInfo":"Intel Core i7-9700K 3.6Ghz Socket 1151 procesor","itemPrice":2596,"itemStartPrice":2596,"percentChange":0,"priceChange":0,"timeAdded":1594044003181,"timeUpdated":1596895203307,"timeLastSeen":1600092003147,"dateAdded":"06-07-2020","dateUpdated":"14-09-2020","itemLink":"https://www.nabava.net/procesori/intel-core-i7-9700k-36ghz-socket-1151-procesor-cijena-68991051"},{"itemID":"68991071","itemInfo":"Intel Core i9-9900K 3.6Ghz Socket 1151 procesor","itemPrice":3282,"itemStartPrice":3282,"percentChange":0,"priceChange":0,"timeAdded":1594044003181,"timeUpdated":1594044003181,"timeLastSeen":1600092003147,"dateAdded":"06-07-2020","dateUpdated":"14-09-2020","itemLink":"https://www.nabava.net/procesori/intel-core-i9-9900k-36ghz-socket-1151-procesor-cijena-68991071"},{"itemID":"76444011","itemInfo":"Gembird Heatsink thermal paste grease, 3 g weight; Brand: Gembird; Model: ; PartNo: ; GEM-TG-G3.0-01 Gembird Heatsink thermal paste grease - 3 g weight Thermal compund (grease) for heatsinks Helps the heat dissipation from a CPU, chipset or...","itemPrice":26,"itemStartPrice":26,"percentChange":0,"priceChange":0,"timeAdded":1599487203813,"timeUpdated":1599487203813,"timeLastSeen":1600092003147,"dateAdded":"07-09-2020","dateUpdated":"07-09-2020","itemLink":"https://www.nabava.net/procesori/gembird-heatsink-thermal-paste-grease-cijena-3-g-weight-brand-gembird-model-partno-gem-tg-g30-01-gembird-heatsink-thermal-paste-grease-3-g-weight-thermal-compund-grease-for-heatsinks-helps-the-heat-dissipation-from-a-cpu-chipset-or-76444011"},{"itemID":"76444031","itemInfo":"Gembird Heatsink thermal paste grease, 1.5 g weight; Brand: Gembird; Model: ; PartNo: ; GEM-TG-G1.5-01 Gembird Heatsink thermal paste grease - 1.5 g weight Thermal compund (grease) for heatsinks Helps the heat dissipation from a CPU, chipset or...","itemPrice":19,"itemStartPrice":19,"percentChange":0,"priceChange":0,"timeAdded":1599487203813,"timeUpdated":1599487203813,"timeLastSeen":1600092003147,"dateAdded":"07-09-2020","dateUpdated":"07-09-2020","itemLink":"https://www.nabava.net/procesori/gembird-heatsink-thermal-paste-grease-cijena-15-g-weight-brand-gembird-model-partno-gem-tg-g15-01-gembird-heatsink-thermal-paste-grease-15-g-weight-thermal-compund-grease-for-heatsinks-helps-the-heat-dissipation-from-a-cpu-chipset-or-76444031"},{"itemID":"77647371","itemInfo":"AMD Ryzen Threadripper 2950X 3.5Ghz Socket TR4 procesor","itemPrice":7188,"itemStartPrice":7188,"percentChange":0,"priceChange":0,"timeAdded":1594044003181,"timeUpdated":1595426402624,"timeLastSeen":1600092003147,"dateAdded":"06-07-2020","dateUpdated":"10-09-2020","itemLink":"https://www.nabava.net/procesori/amd-ryzen-threadripper-2950x-35ghz-socket-tr4-procesor-cijena-77647371"},{"itemID":"77647391","itemInfo":"AMD Athlon 200GE 3.2Ghz Socket AM4 procesor","itemPrice":383,"itemStartPrice":383,"percentChange":0,"priceChange":0,"timeAdded":1594044003181,"timeUpdated":1599660003647,"timeLastSeen":1600092003147,"dateAdded":"06-07-2020","dateUpdated":"09-09-2020","itemLink":"https://www.nabava.net/procesori/amd-athlon-200ge-32ghz-socket-am4-procesor-cijena-77647391"},{"itemID":"77647411","itemInfo":"AMD Ryzen Threadripper 2970WX 3.0Ghz Socket TR4 procesor","itemPrice":8250,"itemStartPrice":8250,"percentChange":0,"priceChange":0,"timeAdded":1594044003181,"timeUpdated":1597154403212,"timeLastSeen":1600092003147,"dateAdded":"06-07-2020","dateUpdated":"24-08-2020","itemLink":"https://www.nabava.net/procesori/amd-ryzen-threadripper-2970wx-30ghz-socket-tr4-procesor-cijena-77647411"},{"itemID":"77647431","itemInfo":"AMD Ryzen Threadripper 2920X 3.5Ghz Socket TR4 procesor","itemPrice":3999,"itemStartPrice":3501,"percentChange":15,"priceChange":498,"timeAdded":1594044003181,"timeUpdated":1598277603581,"timeLastSeen":1600092003147,"dateAdded":"06-07-2020","dateUpdated":"24-08-2020","itemLink":"https://www.nabava.net/procesori/amd-ryzen-threadripper-2920x-35ghz-socket-tr4-procesor-cijena-77647431"},{"itemID":"77647671","itemInfo":"Intel Xeon W-2125 4.0Ghz Socket 2066 procesor","itemPrice":3766,"itemStartPrice":4399,"percentChange":-15,"priceChange":-633,"timeAdded":1597992838225,"timeUpdated":1599141603573,"timeLastSeen":1600092003147,"dateAdded":"21-08-2020","dateUpdated":"14-09-2020","itemLink":"https://www.nabava.net/procesori/intel-xeon-w-2125-40ghz-socket-2066-procesor-cijena-77647671"},{"itemID":"77647731","itemInfo":"Intel Core i9-9820X 3.3Ghz Socket 2066 procesor","itemPrice":4850,"itemStartPrice":4904,"percentChange":-2,"priceChange":-54,"timeAdded":1594044003181,"timeUpdated":1599314403619,"timeLastSeen":1600092003147,"dateAdded":"06-07-2020","dateUpdated":"10-09-2020","itemLink":"https://www.nabava.net/procesori/intel-core-i9-9820x-33ghz-socket-2066-procesor-cijena-77647731"},{"itemID":"77647751","itemInfo":"Intel Core i9-9900X 3.5Ghz Socket 2066 procesor","itemPrice":4359,"itemStartPrice":4717,"percentChange":-8,"priceChange":-358,"timeAdded":1594044003181,"timeUpdated":1598882402591,"timeLastSeen":1600092003147,"dateAdded":"06-07-2020","dateUpdated":"14-09-2020","itemLink":"https://www.nabava.net/procesori/intel-core-i9-9900x-35ghz-socket-2066-procesor-cijena-77647751"},{"itemID":"77647771","itemInfo":"Intel Core i9-9980XE 3.0Ghz Socket 2066 procesor","itemPrice":7588,"itemStartPrice":7588,"percentChange":0,"priceChange":0,"timeAdded":1594044003181,"timeUpdated":1594044003181,"timeLastSeen":1600092003147,"dateAdded":"06-07-2020","dateUpdated":"10-09-2020","itemLink":"https://www.nabava.net/procesori/intel-core-i9-9980xe-30ghz-socket-2066-procesor-cijena-77647771"},{"itemID":"78612151","itemInfo":"Intel Core i5-9400F 2.9Ghz Socket 1151 procesor","itemPrice":998,"itemStartPrice":998,"percentChange":0,"priceChange":0,"timeAdded":1594044003181,"timeUpdated":1596808804629,"timeLastSeen":1600092003147,"dateAdded":"06-07-2020","dateUpdated":"14-09-2020","itemLink":"https://www.nabava.net/procesori/intel-core-i5-9400f-29ghz-socket-1151-procesor-cijena-78612151"},{"itemID":"78612171","itemInfo":"Intel Core i9-9960X 3.1Ghz Socket 2066 procesor","itemPrice":6771,"itemStartPrice":6771,"percentChange":0,"priceChange":0,"timeAdded":1594044003181,"timeUpdated":1594044003181,"timeLastSeen":1600092003147,"dateAdded":"06-07-2020","dateUpdated":"10-09-2020","itemLink":"https://www.nabava.net/procesori/intel-core-i9-9960x-31ghz-socket-2066-procesor-cijena-78612171"},{"itemID":"78612191","itemInfo":"Intel Core i9-9940X 3.3Ghz Socket 2066 procesor","itemPrice":5877,"itemStartPrice":5877,"percentChange":0,"priceChange":0,"timeAdded":1594044003181,"timeUpdated":1594044003181,"timeLastSeen":1600092003147,"dateAdded":"06-07-2020","dateUpdated":"14-09-2020","itemLink":"https://www.nabava.net/procesori/intel-core-i9-9940x-33ghz-socket-2066-procesor-cijena-78612191"},{"itemID":"78612211","itemInfo":"Intel Xeon W-2123 3.6Ghz Socket 2066 procesor","itemPrice":2483,"itemStartPrice":2483,"percentChange":0,"priceChange":0,"timeAdded":1594044003181,"timeUpdated":1594044003181,"timeLastSeen":1600092003147,"dateAdded":"06-07-2020","dateUpdated":"14-09-2020","itemLink":"https://www.nabava.net/procesori/intel-xeon-w-2123-36ghz-socket-2066-procesor-cijena-78612211"},{"itemID":"78612231","itemInfo":"Intel Intel Xeon W-2145 3.7Ghz Socket 2066 procesor","itemPrice":9280,"itemStartPrice":9280,"percentChange":0,"priceChange":0,"timeAdded":1594044003181,"timeUpdated":1594044003181,"timeLastSeen":1600092003147,"dateAdded":"06-07-2020","dateUpdated":"14-09-2020","itemLink":"https://www.nabava.net/procesori/intel-intel-xeon-w-2145-37ghz-socket-2066-procesor-cijena-78612231"},{"itemID":"78612251","itemInfo":"Intel Intel Xeon W-2135 3.7Ghz Socket 2066 procesor","itemPrice":7249,"itemStartPrice":7249,"percentChange":0,"priceChange":0,"timeAdded":1598018403613,"timeUpdated":1598018403613,"timeLastSeen":1600092003147,"dateAdded":"21-08-2020","dateUpdated":"21-08-2020","itemLink":"https://www.nabava.net/procesori/intel-intel-xeon-w-2135-37ghz-socket-2066-procesor-cijena-78612251"},{"itemID":"81839051","itemInfo":"AMD A4-3400 3.4Ghz Socket AM4 procesor","itemPrice":530,"itemStartPrice":530,"percentChange":0,"priceChange":0,"timeAdded":1599919204013,"timeUpdated":1599919204013,"timeLastSeen":1600005603348,"dateAdded":"12-09-2020","dateUpdated":"12-09-2020","itemLink":"https://www.nabava.net/procesori/amd-a4-3400-34ghz-socket-am4-procesor-cijena-81839051"},{"itemID":"83166471","itemInfo":"AMD Athlon 200GE 3.2Ghz Socket AM4 procesor","itemPrice":399,"itemStartPrice":399,"percentChange":0,"priceChange":0,"timeAdded":1594044003181,"timeUpdated":1594044003181,"timeLastSeen":1600092003147,"dateAdded":"06-07-2020","dateUpdated":"06-07-2020","itemLink":"https://www.nabava.net/procesori/amd-athlon-200ge-32ghz-socket-am4-procesor-cijena-83166471"},{"itemID":"85062211","itemInfo":"AMD A6-9400 3.7Ghz Socket AM4 procesor","itemPrice":329,"itemStartPrice":329,"percentChange":0,"priceChange":0,"timeAdded":1599055204505,"timeUpdated":1599055204505,"timeLastSeen":1600092003147,"dateAdded":"02-09-2020","dateUpdated":"02-09-2020","itemLink":"https://www.nabava.net/procesori/amd-a6-9400-37ghz-socket-am4-procesor-cijena-85062211"},{"itemID":"85062251","itemInfo":"Intel Core i7-9700KF 3.6Ghz Socket 1151 procesor","itemPrice":2548,"itemStartPrice":2548,"percentChange":0,"priceChange":0,"timeAdded":1594044003181,"timeUpdated":1596722403709,"timeLastSeen":1600092003147,"dateAdded":"06-07-2020","dateUpdated":"14-09-2020","itemLink":"https://www.nabava.net/procesori/intel-core-i7-9700kf-36ghz-socket-1151-procesor-cijena-85062251"},{"itemID":"86728291","itemInfo":"Intel Xeon Platinum 8160 2.1Ghz Socket 3647 procesor","itemPrice":40699,"itemStartPrice":40699,"percentChange":0,"priceChange":0,"timeAdded":1597992838225,"timeUpdated":1597992838225,"timeLastSeen":1600092003147,"dateAdded":"21-08-2020","dateUpdated":"21-08-2020","itemLink":"https://www.nabava.net/procesori/intel-xeon-platinum-8160-21ghz-socket-3647-procesor-cijena-86728291"},{"itemID":"89984031","itemInfo":"AMD Ryzen 5 3600 3.6Ghz Socket AM4 procesor","itemPrice":1420,"itemStartPrice":1420,"percentChange":0,"priceChange":0,"timeAdded":1594044003181,"timeUpdated":1594303202946,"timeLastSeen":1600092003147,"dateAdded":"06-07-2020","dateUpdated":"10-09-2020","itemLink":"https://www.nabava.net/procesori/amd-ryzen-5-3600-36ghz-socket-am4-procesor-cijena-89984031"},{"itemID":"89984051","itemInfo":"AMD Ryzen 5 3600X 3.8Ghz Socket AM4 procesor","itemPrice":1644,"itemStartPrice":1638,"percentChange":1,"priceChange":6,"timeAdded":1594044003181,"timeUpdated":1599746402721,"timeLastSeen":1600092003147,"dateAdded":"06-07-2020","dateUpdated":"14-09-2020","itemLink":"https://www.nabava.net/procesori/amd-ryzen-5-3600x-38ghz-socket-am4-procesor-cijena-89984051"},{"itemID":"89984151","itemInfo":"AMD Ryzen 7 3700X 3.6Ghz Socket AM4 procesor","itemPrice":2306,"itemStartPrice":2306,"percentChange":0,"priceChange":0,"timeAdded":1594044003181,"timeUpdated":1594044003181,"timeLastSeen":1600092003147,"dateAdded":"06-07-2020","dateUpdated":"14-09-2020","itemLink":"https://www.nabava.net/procesori/amd-ryzen-7-3700x-36ghz-socket-am4-procesor-cijena-89984151"},{"itemID":"89984231","itemInfo":"AMD Ryzen 5 3400G 3.7Ghz Socket AM4 procesor","itemPrice":1086,"itemStartPrice":1086,"percentChange":0,"priceChange":0,"timeAdded":1594044003181,"timeUpdated":1594735203568,"timeLastSeen":1600092003147,"dateAdded":"06-07-2020","dateUpdated":"14-09-2020","itemLink":"https://www.nabava.net/procesori/amd-ryzen-5-3400g-37ghz-socket-am4-procesor-cijena-89984231"},{"itemID":"89984251","itemInfo":"AMD Ryzen 7 3800X 3.9Ghz Socket AM4 procesor","itemPrice":2483,"itemStartPrice":2483,"percentChange":0,"priceChange":0,"timeAdded":1594044003181,"timeUpdated":1595512803258,"timeLastSeen":1600092003147,"dateAdded":"06-07-2020","dateUpdated":"14-09-2020","itemLink":"https://www.nabava.net/procesori/amd-ryzen-7-3800x-39ghz-socket-am4-procesor-cijena-89984251"},{"itemID":"89984291","itemInfo":"Intel Xeon E-2136 3.3Ghz Socket 1151 procesor","itemPrice":2406,"itemStartPrice":2406,"percentChange":0,"priceChange":0,"timeAdded":1594044003181,"timeUpdated":1594044003181,"timeLastSeen":1600092003147,"dateAdded":"06-07-2020","dateUpdated":"14-09-2020","itemLink":"https://www.nabava.net/procesori/intel-xeon-e-2136-33ghz-socket-1151-procesor-cijena-89984291"},{"itemID":"89984311","itemInfo":"Intel Core i9-9900KF 3.6Ghz Socket 1151 procesor","itemPrice":2965,"itemStartPrice":3819,"percentChange":-23,"priceChange":-854,"timeAdded":1594044003181,"timeUpdated":1597672803971,"timeLastSeen":1600092003147,"dateAdded":"06-07-2020","dateUpdated":"14-09-2020","itemLink":"https://www.nabava.net/procesori/intel-core-i9-9900kf-36ghz-socket-1151-procesor-cijena-89984311"},{"itemID":"89984351","itemInfo":"AMD Ryzen 3 3200G 3.6Ghz Socket AM4 procesor","itemPrice":807,"itemStartPrice":721,"percentChange":12,"priceChange":86,"timeAdded":1594044003181,"timeUpdated":1599055204505,"timeLastSeen":1600092003147,"dateAdded":"06-07-2020","dateUpdated":"06-09-2020","itemLink":"https://www.nabava.net/procesori/amd-ryzen-3-3200g-36ghz-socket-am4-procesor-cijena-89984351"},{"itemID":"89984491","itemInfo":"AMD Ryzen 9 3900X 3.8Ghz Socket AM4 procesor","itemPrice":3348,"itemStartPrice":3427,"percentChange":-3,"priceChange":-79,"timeAdded":1594044003181,"timeUpdated":1599141603573,"timeLastSeen":1600092003147,"dateAdded":"06-07-2020","dateUpdated":"14-09-2020","itemLink":"https://www.nabava.net/procesori/amd-ryzen-9-3900x-38ghz-socket-am4-procesor-cijena-89984491"},{"itemID":"89984571","itemInfo":"AMD Athlon 220GE 3.4Ghz Socket AM4 procesor","itemPrice":560,"itemStartPrice":511,"percentChange":10,"priceChange":49,"timeAdded":1594044003181,"timeUpdated":1600005603348,"timeLastSeen":1600092003147,"dateAdded":"06-07-2020","dateUpdated":"13-09-2020","itemLink":"https://www.nabava.net/procesori/amd-athlon-220ge-34ghz-socket-am4-procesor-cijena-89984571"},{"itemID":"89984751","itemInfo":"Intel Core i5-9600KF 3.7Ghz Socket 1151 procesor","itemPrice":1492,"itemStartPrice":1492,"percentChange":0,"priceChange":0,"timeAdded":1594044003181,"timeUpdated":1597240805371,"timeLastSeen":1600092003147,"dateAdded":"06-07-2020","dateUpdated":"14-09-2020","itemLink":"https://www.nabava.net/procesori/intel-core-i5-9600kf-37ghz-socket-1151-procesor-cijena-89984751"},{"itemID":"89984831","itemInfo":"Intel Core i7-9800X 3.8Ghz Socket 2066 procesor","itemPrice":4799,"itemStartPrice":5023,"percentChange":-5,"priceChange":-224,"timeAdded":1594044003181,"timeUpdated":1599660003647,"timeLastSeen":1600092003147,"dateAdded":"06-07-2020","dateUpdated":"09-09-2020","itemLink":"https://www.nabava.net/procesori/intel-core-i7-9800x-38ghz-socket-2066-procesor-cijena-89984831"},{"itemID":"89984851","itemInfo":"Intel Core i5-9400 2.9Ghz Socket 1151 procesor","itemPrice":1230,"itemStartPrice":1234,"percentChange":-1,"priceChange":-4,"timeAdded":1594044003181,"timeUpdated":1599573603320,"timeLastSeen":1600092003147,"dateAdded":"06-07-2020","dateUpdated":"14-09-2020","itemLink":"https://www.nabava.net/procesori/intel-core-i5-9400-29ghz-socket-1151-procesor-cijena-89984851"},{"itemID":"89984871","itemInfo":"Intel Core i3-9100F 3.6Ghz Socket 1151 procesor","itemPrice":538,"itemStartPrice":538,"percentChange":0,"priceChange":0,"timeAdded":1594044003181,"timeUpdated":1596031203407,"timeLastSeen":1600092003147,"dateAdded":"06-07-2020","dateUpdated":"14-09-2020","itemLink":"https://www.nabava.net/procesori/intel-core-i3-9100f-36ghz-socket-1151-procesor-cijena-89984871"},{"itemID":"89984891","itemInfo":"Intel Core i9-9920X 3.5Ghz Socket 2066 procesor","itemPrice":5299,"itemStartPrice":5299,"percentChange":0,"priceChange":0,"timeAdded":1594044003181,"timeUpdated":1594044003181,"timeLastSeen":1600092003147,"dateAdded":"06-07-2020","dateUpdated":"10-09-2020","itemLink":"https://www.nabava.net/procesori/intel-core-i9-9920x-35ghz-socket-2066-procesor-cijena-89984891"},{"itemID":"89984911","itemInfo":"Intel Core i9-9900 3.1Ghz Socket 1151 procesor","itemPrice":2814,"itemStartPrice":2814,"percentChange":0,"priceChange":0,"timeAdded":1594044003181,"timeUpdated":1594044003181,"timeLastSeen":1600092003147,"dateAdded":"06-07-2020","dateUpdated":"14-09-2020","itemLink":"https://www.nabava.net/procesori/intel-core-i9-9900-31ghz-socket-1151-procesor-cijena-89984911"},{"itemID":"89985031","itemInfo":"Intel Xeon E-2134 3.5Ghz Socket 1151 procesor","itemPrice":2102,"itemStartPrice":2102,"percentChange":0,"priceChange":0,"timeAdded":1597327203321,"timeUpdated":1597327203321,"timeLastSeen":1599919204013,"dateAdded":"13-08-2020","dateUpdated":"12-09-2020","itemLink":"https://www.nabava.net/procesori/intel-xeon-e-2134-35ghz-socket-1151-procesor-cijena-89985031"},{"itemID":"89985071","itemInfo":"Intel Core i7-9700 3.0Ghz Socket 1151 procesor","itemPrice":2162,"itemStartPrice":2162,"percentChange":0,"priceChange":0,"timeAdded":1594044003181,"timeUpdated":1596463203810,"timeLastSeen":1600092003147,"dateAdded":"06-07-2020","dateUpdated":"14-09-2020","itemLink":"https://www.nabava.net/procesori/intel-core-i7-9700-30ghz-socket-1151-procesor-cijena-89985071"},{"itemID":"89985091","itemInfo":"Intel Core i7-9700F 3.0Ghz Socket 1151 procesor","itemPrice":2182,"itemStartPrice":2182,"percentChange":0,"priceChange":0,"timeAdded":1594044003181,"timeUpdated":1596895203307,"timeLastSeen":1600092003147,"dateAdded":"06-07-2020","dateUpdated":"14-09-2020","itemLink":"https://www.nabava.net/procesori/intel-core-i7-9700f-30ghz-socket-1151-procesor-cijena-89985091"},{"itemID":"89985111","itemInfo":"Intel Core i5-9500F 3.0Ghz Socket 1151 procesor","itemPrice":1207,"itemStartPrice":1282,"percentChange":-6,"priceChange":-75,"timeAdded":1594044003181,"timeUpdated":1599228003934,"timeLastSeen":1600092003147,"dateAdded":"06-07-2020","dateUpdated":"14-09-2020","itemLink":"https://www.nabava.net/procesori/intel-core-i5-9500f-30ghz-socket-1151-procesor-cijena-89985111"},{"itemID":"89985131","itemInfo":"Intel Core i5-9500 3.0Ghz Socket 1151 procesor","itemPrice":1527,"itemStartPrice":1607,"percentChange":-5,"priceChange":-80,"timeAdded":1594044003181,"timeUpdated":1599746402721,"timeLastSeen":1600092003147,"dateAdded":"06-07-2020","dateUpdated":"14-09-2020","itemLink":"https://www.nabava.net/procesori/intel-core-i5-9500-30ghz-socket-1151-procesor-cijena-89985131"},{"itemID":"89985151","itemInfo":"Intel Core i3-9350KF 4.0Ghz Socket 1151 procesor","itemPrice":1249,"itemStartPrice":1249,"percentChange":0,"priceChange":0,"timeAdded":1594044003181,"timeUpdated":1596031203407,"timeLastSeen":1600092003147,"dateAdded":"06-07-2020","dateUpdated":"14-09-2020","itemLink":"https://www.nabava.net/procesori/intel-core-i3-9350kf-40ghz-socket-1151-procesor-cijena-89985151"},{"itemID":"89985191","itemInfo":"Intel Core i3-9100 3.6Ghz Socket 1151 procesor","itemPrice":806,"itemStartPrice":806,"percentChange":0,"priceChange":0,"timeAdded":1594044003181,"timeUpdated":1596031203407,"timeLastSeen":1600092003147,"dateAdded":"06-07-2020","dateUpdated":"14-09-2020","itemLink":"https://www.nabava.net/procesori/intel-core-i3-9100-36ghz-socket-1151-procesor-cijena-89985191"},{"itemID":"92573871","itemInfo":"Intel Pentium G5400T 3.1Ghz Socket 1151 procesor","itemPrice":517,"itemStartPrice":420,"percentChange":24,"priceChange":97,"timeAdded":1594044003181,"timeUpdated":1598882402591,"timeLastSeen":1600092003147,"dateAdded":"06-07-2020","dateUpdated":"03-09-2020","itemLink":"https://www.nabava.net/procesori/intel-pentium-g5400t-31ghz-socket-1151-procesor-cijena-92573871"},{"itemID":"92807811","itemInfo":"Intel Pentium G5420 3.8Ghz Socket 1151 procesor","itemPrice":420,"itemStartPrice":420,"percentChange":0,"priceChange":0,"timeAdded":1594044003181,"timeUpdated":1594044003181,"timeLastSeen":1600092003147,"dateAdded":"06-07-2020","dateUpdated":"09-09-2020","itemLink":"https://www.nabava.net/procesori/intel-pentium-g5420-38ghz-socket-1151-procesor-cijena-92807811"},{"itemID":"94951091","itemInfo":"Intel Xeon Silver 4214 2.2Ghz Socket 3647 procesor","itemPrice":5750,"itemStartPrice":5750,"percentChange":0,"priceChange":0,"timeAdded":1594044003181,"timeUpdated":1594044003181,"timeLastSeen":1600092003147,"dateAdded":"06-07-2020","dateUpdated":"14-09-2020","itemLink":"https://www.nabava.net/procesori/intel-xeon-silver-4214-22ghz-socket-3647-procesor-cijena-94951091"},{"itemID":"96101431","itemInfo":"Intel Xeon Silver 4210 2.2Ghz Socket 3647 procesor","itemPrice":4151,"itemStartPrice":4129,"percentChange":1,"priceChange":22,"timeAdded":1599055204505,"timeUpdated":1599055204505,"timeLastSeen":1600092003147,"dateAdded":"02-09-2020","dateUpdated":"14-09-2020","itemLink":"https://www.nabava.net/procesori/intel-xeon-silver-4210-22ghz-socket-3647-procesor-cijena-96101431"},{"itemID":"96101451","itemInfo":"Intel Xeon Gold 6252 2.1Ghz Socket 3647 procesor","itemPrice":30716,"itemStartPrice":30403,"percentChange":2,"priceChange":313,"timeAdded":1598968803733,"timeUpdated":1598968803733,"timeLastSeen":1600092003147,"dateAdded":"01-09-2020","dateUpdated":"14-09-2020","itemLink":"https://www.nabava.net/procesori/intel-xeon-gold-6252-21ghz-socket-3647-procesor-cijena-96101451"},{"itemID":"98214151","itemInfo":"AMD Ryzen 9 3950X 3.5Ghz Socket AM4 procesor","itemPrice":5882,"itemStartPrice":5799,"percentChange":2,"priceChange":83,"timeAdded":1599055204505,"timeUpdated":1599055204505,"timeLastSeen":1600092003147,"dateAdded":"02-09-2020","dateUpdated":"14-09-2020","itemLink":"https://www.nabava.net/procesori/amd-ryzen-9-3950x-35ghz-socket-am4-procesor-cijena-98214151"},{"itemID":"106833851","itemInfo":"Intel Core i9-10940X 3.3Ghz Socket 2066 procesor","itemPrice":6432,"itemStartPrice":6550,"percentChange":-2,"priceChange":-118,"timeAdded":1599055204505,"timeUpdated":1599055204505,"timeLastSeen":1600092003147,"dateAdded":"02-09-2020","dateUpdated":"14-09-2020","itemLink":"https://www.nabava.net/procesori/intel-core-i9-10940x-33ghz-socket-2066-procesor-cijena-106833851"},{"itemID":"106833941","itemInfo":"Intel Celeron G4930 3.2Ghz Socket 1151 procesor","itemPrice":278,"itemStartPrice":275,"percentChange":2,"priceChange":3,"timeAdded":1599055204505,"timeUpdated":1599055204505,"timeLastSeen":1600092003147,"dateAdded":"02-09-2020","dateUpdated":"10-09-2020","itemLink":"https://www.nabava.net/procesori/intel-celeron-g4930-32ghz-socket-1151-procesor-cijena-106833941"},{"itemID":"106833971","itemInfo":"Intel Core i5-3550S 3.0Ghz Socket 1155 procesor","itemPrice":2149,"itemStartPrice":2149,"percentChange":0,"priceChange":0,"timeAdded":1599055204505,"timeUpdated":1599055204505,"timeLastSeen":1600092003147,"dateAdded":"02-09-2020","dateUpdated":"02-09-2020","itemLink":"https://www.nabava.net/procesori/intel-core-i5-3550s-30ghz-socket-1155-procesor-cijena-106833971"},{"itemID":"106834001","itemInfo":"Intel Pentium Gold G5600F 3.9Ghz Socket 1151 procesor","itemPrice":629,"itemStartPrice":630,"percentChange":-1,"priceChange":-1,"timeAdded":1599055204505,"timeUpdated":1599055204505,"timeLastSeen":1600092003147,"dateAdded":"02-09-2020","dateUpdated":"14-09-2020","itemLink":"https://www.nabava.net/procesori/intel-pentium-gold-g5600f-39ghz-socket-1151-procesor-cijena-106834001"},{"itemID":"106834031","itemInfo":"Intel Core i9-10900X 3.7Ghz Socket 2066 procesor","itemPrice":4917,"itemStartPrice":4925,"percentChange":-1,"priceChange":-8,"timeAdded":1599055204505,"timeUpdated":1599055204505,"timeLastSeen":1600092003147,"dateAdded":"02-09-2020","dateUpdated":"14-09-2020","itemLink":"https://www.nabava.net/procesori/intel-core-i9-10900x-37ghz-socket-2066-procesor-cijena-106834031"},{"itemID":"106834061","itemInfo":"Intel Xeon 4210 2.2Ghz Socket 3647 procesor","itemPrice":4155,"itemStartPrice":4117,"percentChange":1,"priceChange":38,"timeAdded":1599055204505,"timeUpdated":1599055204505,"timeLastSeen":1600092003147,"dateAdded":"02-09-2020","dateUpdated":"11-09-2020","itemLink":"https://www.nabava.net/procesori/intel-xeon-4210-22ghz-socket-3647-procesor-cijena-106834061"},{"itemID":"106834091","itemInfo":"Intel Xeon E5-2658 2.1Ghz Socket 2011 procesor","itemPrice":3950,"itemStartPrice":3950,"percentChange":0,"priceChange":0,"timeAdded":1599055204505,"timeUpdated":1599055204505,"timeLastSeen":1600092003147,"dateAdded":"02-09-2020","dateUpdated":"02-09-2020","itemLink":"https://www.nabava.net/procesori/intel-xeon-e5-2658-21ghz-socket-2011-procesor-cijena-106834091"},{"itemID":"106834121","itemInfo":"Intel Xeon Gold 6130 2.1Ghz Socket 3647 procesor","itemPrice":16399,"itemStartPrice":16399,"percentChange":0,"priceChange":0,"timeAdded":1598968803733,"timeUpdated":1598968803733,"timeLastSeen":1600092003147,"dateAdded":"01-09-2020","dateUpdated":"01-09-2020","itemLink":"https://www.nabava.net/procesori/intel-xeon-gold-6130-21ghz-socket-3647-procesor-cijena-106834121"},{"itemID":"106834181","itemInfo":"Intel Core i9-10920X 3.5Ghz Socket 2066 procesor","itemPrice":5487,"itemStartPrice":5565,"percentChange":-2,"priceChange":-78,"timeAdded":1599055204505,"timeUpdated":1599055204505,"timeLastSeen":1600092003147,"dateAdded":"02-09-2020","dateUpdated":"14-09-2020","itemLink":"https://www.nabava.net/procesori/intel-core-i9-10920x-35ghz-socket-2066-procesor-cijena-106834181"},{"itemID":"106834211","itemInfo":"Intel Pentium Gold G5420 3.8Ghz Socket 1151 procesor","itemPrice":449,"itemStartPrice":449,"percentChange":0,"priceChange":0,"timeAdded":1599055204505,"timeUpdated":1599055204505,"timeLastSeen":1600092003147,"dateAdded":"02-09-2020","dateUpdated":"02-09-2020","itemLink":"https://www.nabava.net/procesori/intel-pentium-gold-g5420-38ghz-socket-1151-procesor-cijena-106834211"},{"itemID":"106834241","itemInfo":"AMD Athlon 3000G Socket AM4 procesor","itemPrice":399,"itemStartPrice":372,"percentChange":8,"priceChange":27,"timeAdded":1594044003181,"timeUpdated":1599660003647,"timeLastSeen":1600092003147,"dateAdded":"06-07-2020","dateUpdated":"09-09-2020","itemLink":"https://www.nabava.net/procesori/amd-athlon-3000g-socket-am4-procesor-cijena-106834241"},{"itemID":"106834271","itemInfo":"AMD Ryzen Threadripper 3960X 3.8Ghz Socket sTRX4 procesor","itemPrice":10710,"itemStartPrice":10336,"percentChange":4,"priceChange":374,"timeAdded":1599055204505,"timeUpdated":1599055204505,"timeLastSeen":1600092003147,"dateAdded":"02-09-2020","dateUpdated":"10-09-2020","itemLink":"https://www.nabava.net/procesori/amd-ryzen-threadripper-3960x-38ghz-socket-strx4-procesor-cijena-106834271"},{"itemID":"106834301","itemInfo":"AMD Ryzen Threadripper 3970X 3.7Ghz Socket sTRX4 procesor","itemPrice":14745,"itemStartPrice":14770,"percentChange":-1,"priceChange":-25,"timeAdded":1599055204505,"timeUpdated":1599055204505,"timeLastSeen":1600092003147,"dateAdded":"02-09-2020","dateUpdated":"14-09-2020","itemLink":"https://www.nabava.net/procesori/amd-ryzen-threadripper-3970x-37ghz-socket-strx4-procesor-cijena-106834301"},{"itemID":"106834331","itemInfo":"AMD Ryzen Threadripper 3990X 2.9Ghz Socket sTRX4 procesor","itemPrice":30722,"itemStartPrice":30668,"percentChange":1,"priceChange":54,"timeAdded":1599055204505,"timeUpdated":1599055204505,"timeLastSeen":1600092003147,"dateAdded":"02-09-2020","dateUpdated":"12-09-2020","itemLink":"https://www.nabava.net/procesori/amd-ryzen-threadripper-3990x-29ghz-socket-strx4-procesor-cijena-106834331"},{"itemID":"107405621","itemInfo":"ThinkSystem ST550 Intel Xeon Silver 4210 Processor","itemPrice":6366,"itemStartPrice":6366,"percentChange":0,"priceChange":0,"timeAdded":1594044003181,"timeUpdated":1596808804629,"timeLastSeen":1600092003147,"dateAdded":"06-07-2020","dateUpdated":"07-08-2020","itemLink":"https://www.nabava.net/procesori/thinksystem-st550-intel-xeon-silver-4210-processor-cijena-107405621"},{"itemID":"108495701","itemInfo":"Intel Core i7-8700T 2.4Ghz Socket 1151 procesor","itemPrice":3549,"itemStartPrice":3549,"percentChange":0,"priceChange":0,"timeAdded":1598968803733,"timeUpdated":1598968803733,"timeLastSeen":1600092003147,"dateAdded":"01-09-2020","dateUpdated":"01-09-2020","itemLink":"https://www.nabava.net/procesori/intel-core-i7-8700t-24ghz-socket-1151-procesor-cijena-108495701"},{"itemID":"108600671","itemInfo":"AMD Ryzen 5 3400G mit Radeon Vega 11 Grafikkarte - 4x 3.70GHz, boxed","itemPrice":1330,"itemStartPrice":1330,"percentChange":0,"priceChange":0,"timeAdded":1597500003018,"timeUpdated":1597500003018,"timeLastSeen":1600092003147,"dateAdded":"15-08-2020","dateUpdated":"15-08-2020","itemLink":"https://www.nabava.net/procesori/amd-ryzen-5-3400g-mit-radeon-vega-11-grafikkarte-4x-370ghz-cijena-boxed-108600671"},{"itemID":"109467131","itemInfo":"Riotoro BIFROST 240 Liquid CPU Cooler; Brand: Corsair; Model: ; PartNo: ; RIO-TR-240 Riotoro BIFROST 240 Liquid CPU Cooler - - 1x BIFROST 240 Unit - 2x 120x25 mm Static Pressure Fans - 1x Accessories Spare Parts - Installation Brackets (AMD...","itemPrice":629,"itemStartPrice":629,"percentChange":0,"priceChange":0,"timeAdded":1599487203813,"timeUpdated":1599487203813,"timeLastSeen":1600092003147,"dateAdded":"07-09-2020","dateUpdated":"07-09-2020","itemLink":"https://www.nabava.net/procesori/riotoro-bifrost-240-liquid-cpu-cooler-brand-corsair-model-partno-rio-tr-240-riotoro-bifrost-240-liquid-cpu-cooler-1x-bifrost-240-unit-2x-120x25-mm-static-pressure-fans-1x-accessories-spare-parts-installation-brackets-amd-cijena-109467131"},{"itemID":"112027301","itemInfo":"Intel Core i7-6700T 2.8Ghz Socket 1151 procesor","itemPrice":3100,"itemStartPrice":936,"percentChange":232,"priceChange":2164,"timeAdded":1596463203810,"timeUpdated":1599746402721,"timeLastSeen":1600092003147,"dateAdded":"03-08-2020","dateUpdated":"13-09-2020","itemLink":"https://www.nabava.net/procesori/intel-core-i7-6700t-28ghz-socket-1151-procesor-cijena-112027301"},{"itemID":"115925651","itemInfo":"Intel Core i3-10100 3.6Ghz Socket 1200 procesor","itemPrice":918,"itemStartPrice":931,"percentChange":-2,"priceChange":-13,"timeAdded":1599055204505,"timeUpdated":1599055204505,"timeLastSeen":1600092003147,"dateAdded":"02-09-2020","dateUpdated":"14-09-2020","itemLink":"https://www.nabava.net/procesori/intel-core-i3-10100-36ghz-socket-1200-procesor-cijena-115925651"},{"itemID":"115925681","itemInfo":"Intel Core i3-10300 3.7Ghz Socket 1200 procesor","itemPrice":1146,"itemStartPrice":1189,"percentChange":-4,"priceChange":-43,"timeAdded":1599055204505,"timeUpdated":1599055204505,"timeLastSeen":1600092003147,"dateAdded":"02-09-2020","dateUpdated":"14-09-2020","itemLink":"https://www.nabava.net/procesori/intel-core-i3-10300-37ghz-socket-1200-procesor-cijena-115925681"},{"itemID":"115925711","itemInfo":"Intel Core i3-10320 3.8Ghz Socket 1200 procesor","itemPrice":1265,"itemStartPrice":1258,"percentChange":1,"priceChange":7,"timeAdded":1599055204505,"timeUpdated":1599055204505,"timeLastSeen":1600092003147,"dateAdded":"02-09-2020","dateUpdated":"14-09-2020","itemLink":"https://www.nabava.net/procesori/intel-core-i3-10320-38ghz-socket-1200-procesor-cijena-115925711"},{"itemID":"115925741","itemInfo":"Intel Core i3-9300 3.7Ghz Socket 1151 procesor","itemPrice":1080,"itemStartPrice":1079,"percentChange":1,"priceChange":1,"timeAdded":1598968803733,"timeUpdated":1598968803733,"timeLastSeen":1600092003147,"dateAdded":"01-09-2020","dateUpdated":"14-09-2020","itemLink":"https://www.nabava.net/procesori/intel-core-i3-9300-37ghz-socket-1151-procesor-cijena-115925741"},{"itemID":"115925771","itemInfo":"Intel Core i5-10400F 2.9Ghz Socket 1200 procesor","itemPrice":1233,"itemStartPrice":1209,"percentChange":2,"priceChange":24,"timeAdded":1599055204505,"timeUpdated":1599746402721,"timeLastSeen":1600092003147,"dateAdded":"02-09-2020","dateUpdated":"13-09-2020","itemLink":"https://www.nabava.net/procesori/intel-core-i5-10400f-29ghz-socket-1200-procesor-cijena-115925771"},{"itemID":"115925801","itemInfo":"Intel Core i5-10400 2.9Ghz Socket 1200 procesor","itemPrice":1303,"itemStartPrice":1311,"percentChange":-1,"priceChange":-8,"timeAdded":1599055204505,"timeUpdated":1599055204505,"timeLastSeen":1600092003147,"dateAdded":"02-09-2020","dateUpdated":"14-09-2020","itemLink":"https://www.nabava.net/procesori/intel-core-i5-10400-29ghz-socket-1200-procesor-cijena-115925801"},{"itemID":"115925831","itemInfo":"Intel Core i5-10600K 4.1Ghz Socket 1200 procesor","itemPrice":2058,"itemStartPrice":2033,"percentChange":2,"priceChange":25,"timeAdded":1599055204505,"timeUpdated":1599055204505,"timeLastSeen":1600092003147,"dateAdded":"02-09-2020","dateUpdated":"14-09-2020","itemLink":"https://www.nabava.net/procesori/intel-core-i5-10600k-41ghz-socket-1200-procesor-cijena-115925831"},{"itemID":"115925861","itemInfo":"Intel Core i5-10600 3.3Ghz Socket 1200 procesor","itemPrice":1758,"itemStartPrice":1836,"percentChange":-5,"priceChange":-78,"timeAdded":1599055204505,"timeUpdated":1599055204505,"timeLastSeen":1600092003147,"dateAdded":"02-09-2020","dateUpdated":"14-09-2020","itemLink":"https://www.nabava.net/procesori/intel-core-i5-10600-33ghz-socket-1200-procesor-cijena-115925861"},{"itemID":"115925951","itemInfo":"Intel Core i5-10500 3.1Ghz Socket 1200 procesor","itemPrice":1528,"itemStartPrice":1592,"percentChange":-5,"priceChange":-64,"timeAdded":1599055204505,"timeUpdated":1599055204505,"timeLastSeen":1600092003147,"dateAdded":"02-09-2020","dateUpdated":"14-09-2020","itemLink":"https://www.nabava.net/procesori/intel-core-i5-10500-31ghz-socket-1200-procesor-cijena-115925951"},{"itemID":"115925981","itemInfo":"Intel Core i5-9600 3.1Ghz Socket 1151 procesor","itemPrice":1736,"itemStartPrice":1720,"percentChange":1,"priceChange":16,"timeAdded":1598968803733,"timeUpdated":1598968803733,"timeLastSeen":1600092003147,"dateAdded":"01-09-2020","dateUpdated":"14-09-2020","itemLink":"https://www.nabava.net/procesori/intel-core-i5-9600-31ghz-socket-1151-procesor-cijena-115925981"},{"itemID":"115926011","itemInfo":"Intel Core i5-10600KF 4.1Ghz Socket 1200 procesor","itemPrice":2170,"itemStartPrice":2169,"percentChange":1,"priceChange":1,"timeAdded":1599055204505,"timeUpdated":1599055204505,"timeLastSeen":1600092003147,"dateAdded":"02-09-2020","dateUpdated":"14-09-2020","itemLink":"https://www.nabava.net/procesori/intel-core-i5-10600kf-41ghz-socket-1200-procesor-cijena-115926011"},{"itemID":"115926041","itemInfo":"Intel Core i7-10700 2.9Ghz Socket 1200 procesor","itemPrice":2419,"itemStartPrice":2497,"percentChange":-4,"priceChange":-78,"timeAdded":1599055204505,"timeUpdated":1599055204505,"timeLastSeen":1600092003147,"dateAdded":"02-09-2020","dateUpdated":"14-09-2020","itemLink":"https://www.nabava.net/procesori/intel-core-i7-10700-29ghz-socket-1200-procesor-cijena-115926041"},{"itemID":"115926071","itemInfo":"Intel Core i7-10700K 3.8Ghz Socket 1200 procesor","itemPrice":3089,"itemStartPrice":2954,"percentChange":5,"priceChange":135,"timeAdded":1599055204505,"timeUpdated":1599055204505,"timeLastSeen":1600092003147,"dateAdded":"02-09-2020","dateUpdated":"14-09-2020","itemLink":"https://www.nabava.net/procesori/intel-core-i7-10700k-38ghz-socket-1200-procesor-cijena-115926071"},{"itemID":"115926101","itemInfo":"Intel Core i7-10700KF 3.8Ghz Socket 1200 procesor","itemPrice":3005,"itemStartPrice":3134,"percentChange":-5,"priceChange":-129,"timeAdded":1598968803733,"timeUpdated":1598968803733,"timeLastSeen":1600092003147,"dateAdded":"01-09-2020","dateUpdated":"14-09-2020","itemLink":"https://www.nabava.net/procesori/intel-core-i7-10700kf-38ghz-socket-1200-procesor-cijena-115926101"},{"itemID":"115926131","itemInfo":"Intel Core i7-10700F 2.9Ghz Socket 1200 procesor","itemPrice":2717,"itemStartPrice":2762,"percentChange":-2,"priceChange":-45,"timeAdded":1598968803733,"timeUpdated":1598968803733,"timeLastSeen":1600092003147,"dateAdded":"01-09-2020","dateUpdated":"14-09-2020","itemLink":"https://www.nabava.net/procesori/intel-core-i7-10700f-29ghz-socket-1200-procesor-cijena-115926131"},{"itemID":"115926161","itemInfo":"Intel Core i9-10900F 2.8Ghz Socket 1200 procesor","itemPrice":3510,"itemStartPrice":3623,"percentChange":-4,"priceChange":-113,"timeAdded":1598968803733,"timeUpdated":1598968803733,"timeLastSeen":1600092003147,"dateAdded":"01-09-2020","dateUpdated":"14-09-2020","itemLink":"https://www.nabava.net/procesori/intel-core-i9-10900f-28ghz-socket-1200-procesor-cijena-115926161"},{"itemID":"115926191","itemInfo":"Intel Core i9-10850K 3.6Ghz Socket 1200 procesor","itemPrice":3868,"itemStartPrice":3837,"percentChange":1,"priceChange":31,"timeAdded":1599055204505,"timeUpdated":1599055204505,"timeLastSeen":1600092003147,"dateAdded":"02-09-2020","dateUpdated":"14-09-2020","itemLink":"https://www.nabava.net/procesori/intel-core-i9-10850k-36ghz-socket-1200-procesor-cijena-115926191"},{"itemID":"115926221","itemInfo":"Intel Core i9-10900K 3.7Ghz Socket 1200 procesor","itemPrice":5001,"itemStartPrice":5184,"percentChange":-4,"priceChange":-183,"timeAdded":1599055204505,"timeUpdated":1599228003934,"timeLastSeen":1600092003147,"dateAdded":"02-09-2020","dateUpdated":"14-09-2020","itemLink":"https://www.nabava.net/procesori/intel-core-i9-10900k-37ghz-socket-1200-procesor-cijena-115926221"},{"itemID":"115926251","itemInfo":"Intel Core i9-10900 2.8Ghz Socket 1200 procesor","itemPrice":3705,"itemStartPrice":3705,"percentChange":0,"priceChange":0,"timeAdded":1598968803733,"timeUpdated":1598968803733,"timeLastSeen":1600092003147,"dateAdded":"01-09-2020","dateUpdated":"07-09-2020","itemLink":"https://www.nabava.net/procesori/intel-core-i9-10900-28ghz-socket-1200-procesor-cijena-115926251"},{"itemID":"115926281","itemInfo":"Intel Celeron G5920 3.5Ghz Socket 1200 procesor","itemPrice":393,"itemStartPrice":430,"percentChange":-9,"priceChange":-37,"timeAdded":1598968803733,"timeUpdated":1599055204505,"timeLastSeen":1600092003147,"dateAdded":"01-09-2020","dateUpdated":"10-09-2020","itemLink":"https://www.nabava.net/procesori/intel-celeron-g5920-35ghz-socket-1200-procesor-cijena-115926281"},{"itemID":"115926311","itemInfo":"Intel Xeon W-2295 3.0Ghz Socket 2066 procesor","itemPrice":11132,"itemStartPrice":11040,"percentChange":1,"priceChange":92,"timeAdded":1599055204505,"timeUpdated":1599055204505,"timeLastSeen":1600092003147,"dateAdded":"02-09-2020","dateUpdated":"14-09-2020","itemLink":"https://www.nabava.net/procesori/intel-xeon-w-2295-30ghz-socket-2066-procesor-cijena-115926311"},{"itemID":"115926341","itemInfo":"Intel Xeon W-2265 3.5Ghz Socket 2066 procesor","itemPrice":7586,"itemStartPrice":7546,"percentChange":1,"priceChange":40,"timeAdded":1599055204505,"timeUpdated":1599055204505,"timeLastSeen":1600092003147,"dateAdded":"02-09-2020","dateUpdated":"14-09-2020","itemLink":"https://www.nabava.net/procesori/intel-xeon-w-2265-35ghz-socket-2066-procesor-cijena-115926341"},{"itemID":"115926371","itemInfo":"Intel Celeron G5900 3.4Ghz Socket 1200 procesor","itemPrice":293,"itemStartPrice":283,"percentChange":4,"priceChange":10,"timeAdded":1598968803733,"timeUpdated":1598968803733,"timeLastSeen":1600092003147,"dateAdded":"01-09-2020","dateUpdated":"02-09-2020","itemLink":"https://www.nabava.net/procesori/intel-celeron-g5900-34ghz-socket-1200-procesor-cijena-115926371"},{"itemID":"115926401","itemInfo":"Intel Pentium Gold G6400 4.0Ghz Socket 1200 procesor","itemPrice":462,"itemStartPrice":447,"percentChange":4,"priceChange":15,"timeAdded":1599055204505,"timeUpdated":1599055204505,"timeLastSeen":1600092003147,"dateAdded":"02-09-2020","dateUpdated":"09-09-2020","itemLink":"https://www.nabava.net/procesori/intel-pentium-gold-g6400-40ghz-socket-1200-procesor-cijena-115926401"},{"itemID":"115926431","itemInfo":"Intel Xeon Silver 4208 2.1Ghz Socket 3647 procesor","itemPrice":3507,"itemStartPrice":3479,"percentChange":1,"priceChange":28,"timeAdded":1599055204505,"timeUpdated":1599055204505,"timeLastSeen":1600092003147,"dateAdded":"02-09-2020","dateUpdated":"14-09-2020","itemLink":"https://www.nabava.net/procesori/intel-xeon-silver-4208-21ghz-socket-3647-procesor-cijena-115926431"},{"itemID":"115926461","itemInfo":"Intel Xeon E-2176G 3.7Ghz Socket 1151 procesor","itemPrice":2979,"itemStartPrice":3850,"percentChange":-23,"priceChange":-871,"timeAdded":1598968803733,"timeUpdated":1599055204505,"timeLastSeen":1600092003147,"dateAdded":"01-09-2020","dateUpdated":"14-09-2020","itemLink":"https://www.nabava.net/procesori/intel-xeon-e-2176g-37ghz-socket-1151-procesor-cijena-115926461"},{"itemID":"115926491","itemInfo":"AMD Ryzen 3 3100 3.6Ghz Socket AM4 procesor","itemPrice":814,"itemStartPrice":793,"percentChange":3,"priceChange":21,"timeAdded":1599055204505,"timeUpdated":1599055204505,"timeLastSeen":1600092003147,"dateAdded":"02-09-2020","dateUpdated":"14-09-2020","itemLink":"https://www.nabava.net/procesori/amd-ryzen-3-3100-36ghz-socket-am4-procesor-cijena-115926491"},{"itemID":"115926521","itemInfo":"AMD Ryzen 3 3300X 3.8Ghz Socket AM4 procesor","itemPrice":1299,"itemStartPrice":1199,"percentChange":9,"priceChange":100,"timeAdded":1599055204505,"timeUpdated":1599660003647,"timeLastSeen":1600092003147,"dateAdded":"02-09-2020","dateUpdated":"11-09-2020","itemLink":"https://www.nabava.net/procesori/amd-ryzen-3-3300x-38ghz-socket-am4-procesor-cijena-115926521"},{"itemID":"115926581","itemInfo":"AMD Ryzen 5 Pro 4650G 3.7Ghz Socket AM4 procesor","itemPrice":1499,"itemStartPrice":1499,"percentChange":0,"priceChange":0,"timeAdded":1599055204505,"timeUpdated":1599055204505,"timeLastSeen":1600092003147,"dateAdded":"02-09-2020","dateUpdated":"02-09-2020","itemLink":"https://www.nabava.net/procesori/amd-ryzen-5-pro-4650g-37ghz-socket-am4-procesor-cijena-115926581"},{"itemID":"115926611","itemInfo":"AMD Ryzen 7 Pro 4750G 3.6Ghz Socket AM4 procesor","itemPrice":2399,"itemStartPrice":2399,"percentChange":0,"priceChange":0,"timeAdded":1599055204505,"timeUpdated":1599055204505,"timeLastSeen":1600092003147,"dateAdded":"02-09-2020","dateUpdated":"02-09-2020","itemLink":"https://www.nabava.net/procesori/amd-ryzen-7-pro-4750g-36ghz-socket-am4-procesor-cijena-115926611"},{"itemID":"115926641","itemInfo":"AMD Ryzen 5 Pro 3400G 3.7Ghz Socket AM4 procesor","itemPrice":1139,"itemStartPrice":1199,"percentChange":-6,"priceChange":-60,"timeAdded":1599055204505,"timeUpdated":1599746402721,"timeLastSeen":1600092003147,"dateAdded":"02-09-2020","dateUpdated":"10-09-2020","itemLink":"https://www.nabava.net/procesori/amd-ryzen-5-pro-3400g-37ghz-socket-am4-procesor-cijena-115926641"},{"itemID":"115926671","itemInfo":"AMD A6-3500 procesor","itemPrice":619,"itemStartPrice":619,"percentChange":0,"priceChange":0,"timeAdded":1598968803733,"timeUpdated":1598968803733,"timeLastSeen":1600092003147,"dateAdded":"01-09-2020","dateUpdated":"01-09-2020","itemLink":"https://www.nabava.net/procesori/amd-a6-3500-procesor-cijena-115926671"},{"itemID":"115926701","itemInfo":"AMD Ryzen 7 3800XT 3.9Ghz Socket AM4 procesor","itemPrice":2994,"itemStartPrice":3033,"percentChange":-2,"priceChange":-39,"timeAdded":1599055204505,"timeUpdated":1599055204505,"timeLastSeen":1600092003147,"dateAdded":"02-09-2020","dateUpdated":"14-09-2020","itemLink":"https://www.nabava.net/procesori/amd-ryzen-7-3800xt-39ghz-socket-am4-procesor-cijena-115926701"},{"itemID":"115926731","itemInfo":"AMD Ryzen 9 3900XT 3.8Ghz Socket AM4 procesor","itemPrice":3874,"itemStartPrice":3919,"percentChange":-2,"priceChange":-45,"timeAdded":1599055204505,"timeUpdated":1599055204505,"timeLastSeen":1600092003147,"dateAdded":"02-09-2020","dateUpdated":"14-09-2020","itemLink":"https://www.nabava.net/procesori/amd-ryzen-9-3900xt-38ghz-socket-am4-procesor-cijena-115926731"},{"itemID":"115926761","itemInfo":"Intel Xeon Silver 4210R 2.4Ghz Socket 3647 procesor","itemPrice":4102,"itemStartPrice":4094,"percentChange":1,"priceChange":8,"timeAdded":1599055204505,"timeUpdated":1599055204505,"timeLastSeen":1600092003147,"dateAdded":"02-09-2020","dateUpdated":"13-09-2020","itemLink":"https://www.nabava.net/procesori/intel-xeon-silver-4210r-24ghz-socket-3647-procesor-cijena-115926761"},{"itemID":"116385041","itemInfo":"Corsair Hydro H45 cooling; Brand: Corsair; Model: ; PartNo: ; COR-CW-9060028-WW Corsair Hydro Series H45 - Liquid CPU cooling Copper cold plate Low profile pump 1x 120mm fan (2300rpm) Noise: 31.0 dBA Radiator: 168,50 x 120 x 71mm Socket support:...","itemPrice":421,"itemStartPrice":415,"percentChange":2,"priceChange":6,"timeAdded":1599487203813,"timeUpdated":1599487203813,"timeLastSeen":1600092003147,"dateAdded":"07-09-2020","dateUpdated":"10-09-2020","itemLink":"https://www.nabava.net/procesori/corsair-hydro-h45-cooling-brand-corsair-model-partno-cor-cw-9060028-ww-corsair-hydro-series-h45-liquid-cpu-cooling-copper-cold-plate-low-profile-pump-1x-120mm-fan-2300rpm-noise-310-dba-radiator-168-cijena50-x-120-x-71mm-socket-support--116385041"},{"itemID":"116385071","itemInfo":"Corsair Hydro H60 cooling; Brand: Corsair; Model: ; PartNo: ; COR-CW-9060036-WW Corsair CW-9060036-WW - Hydro Series H60 Liquid CPU cooling Copper base 1x 120mm fan 1700rpm Socket support: Intel 115x, Intel 1366, Intel 2011 2066 AMD AM2 AM3, AMD...","itemPrice":675,"itemStartPrice":664,"percentChange":2,"priceChange":11,"timeAdded":1599487203813,"timeUpdated":1599487203813,"timeLastSeen":1600092003147,"dateAdded":"07-09-2020","dateUpdated":"10-09-2020","itemLink":"https://www.nabava.net/procesori/corsair-hydro-h60-cooling-brand-corsair-model-partno-cor-cw-9060036-ww-corsair-cw-9060036-ww-hydro-series-h60-liquid-cpu-cooling-copper-base-1x-120mm-fan-1700rpm-socket-support-intel-115x-cijena-intel-1366-intel-2011-2066-amd-am2-am3-amd-116385071"},{"itemID":"116385131","itemInfo":"Corsair CoolingHydro H100i RGB; Brand: Corsair; Model: ; PartNo: ; COR-CW-9060042-WW Corsair CW-9060042-WW - Hydro Series H100i RGB PLATINUM SE, RGB magnetic levitation fans, multi zone RGB pump, aluminium radiator, copper base, IClue, rad.:...","itemPrice":1283,"itemStartPrice":1260,"percentChange":2,"priceChange":23,"timeAdded":1599487203813,"timeUpdated":1599487203813,"timeLastSeen":1600092003147,"dateAdded":"07-09-2020","dateUpdated":"10-09-2020","itemLink":"https://www.nabava.net/procesori/corsair-coolinghydro-h100i-rgb-brand-corsair-model-partno-cor-cw-9060042-ww-corsair-cw-9060042-ww-hydro-series-h100i-rgb-platinum-se-cijena-rgb-magnetic-levitation-fans-multi-zone-rgb-pump-aluminium-radiator-116385131"},{"itemID":"116395721","itemInfo":"Corsair CoolingHydro H115i RGB; Brand: Corsair; Model: ; PartNo: ; COR-CW-9060038-WW Corsair CW-9060038-WW - Hydro Series H115i RGB PLATINUM, RGB magnetic levitation fans, multi zone RGB pump, aluminium radiator, copper base, IClue, rad.: 322mm x...","itemPrice":1239,"itemStartPrice":1219,"percentChange":2,"priceChange":20,"timeAdded":1599487203813,"timeUpdated":1599487203813,"timeLastSeen":1600092003147,"dateAdded":"07-09-2020","dateUpdated":"10-09-2020","itemLink":"https://www.nabava.net/procesori/corsair-coolinghydro-h115i-rgb-brand-corsair-model-partno-cor-cw-9060038-ww-corsair-cw-9060038-ww-hydro-series-h115i-rgb-platinum-cijena-rgb-magnetic-levitation-fans-multi-zone-rgb-pump-aluminium-radiator-116395721"},{"itemID":"116999861","itemInfo":"CPU INT Core i5 10400F","itemPrice":1289,"itemStartPrice":1289,"percentChange":0,"priceChange":0,"timeAdded":1600005603348,"timeUpdated":1600005603348,"timeLastSeen":1600092003147,"dateAdded":"13-09-2020","dateUpdated":"13-09-2020","itemLink":"https://www.nabava.net/procesori/cpu-int-core-i5-10400f-cijena-116999861"}]